Workbook

Sheet Datos
B1: Según el estatuto tributario de los impuestos administrados por la dirección general de impuestos nacionales artículo 137, hay un límite a la deducción por depreciación. Para construcciones y edificaciones (obras civiles), la tasa de depreciación fiscal anual es del 2.22%, para maquinaria y equipos, es del 10% y para muebles y enseres es del 10%. Entonces como la tasa se calcula como tasa=1/vida útil, se puede despejar la vida útil como 1/tasa. Para maquinaria y equipos la tasa máxima es 10%, por lo que 1/0.1 = 10 años es la vida útil mínima que se puede ponerle a estos activos. Dado que 20 años son más que 10 años, es totalmente viable poner 20 años como vida útil a la maquinaria y equipo. Esta misma vida útil se puede poner al montaje y el transporte de equipos ya que son costos de puesta en marcha que se capitalizan como parte del costo de la maquinaria. Para los muebles y enseres y obras civiles, utilizaremos la vida útil mínima. | C1: https://leyes.co/se_expide_el_estatuto_tributario_de_los_impuestos_administrados_por_la_direccion_general_de_impuestos_nacionales/137.htm
B3: Inversión en Activos Fijos Inicial
B4: Inversión inicial | C4: millones de COP | D4: Tasa máxima | E4: Vida útil | F4: Nota
B5: Maquinaria y Equipos | C5: 8500 | D5: 0.1 | E5: 20 | F5: Sacado de la nota 13 del PDF
B6: Muebles y Enseres | C6: 2500 | D6: 0.1 | E6: =1/D6 -> 10 | F6: Vida útil mínima
B7: Obras Civiles | C7: 900 | D7: 0.022 | E7: =1/D7 -> 45.454545 | F7: Vida útil mínima
B8: Montaje | C8: 850 | D8: N/A | E8: 20 | F8: Sacado de la nota 13 del PDF
B9: Transporte de Equipos | C9: 1250 | D9: N/A | E9: 20 | F9: Sacado de la nota 13 del PDF
B10: Total Capex Activos Fijos | C10: =SUM(C5:C9) -> 14000
B11: Inversión inicial | C11: millones de COP | D11: ¿Costo hundido?
B12: Estudio de Mercado | C12: 5000 | D12: SI
B13: Estudios Técnicos | C13: 2500 | D13: SI
B14: Costo Avalúo Bodega | C14: 420 | D14: SI
B15: Total | C15: =SUM(C12:C14) -> 7920
B17: Tasa impositiva Colombia | C17: 0.35
B18: Valor en libros de la bodega | C18: 20000 | D18: millones | E18: Pagina 4
B19: Canon arrendamiento anual (10% VM) | C19: =C20*0.1 -> 2800 | D19: millones | E19: Pagina 4 Nota 9
B20: Valor de venta esperado | C20: 28000 | D20: millones | E20: Pagina 5
B21: Mantenimiento sobre activos | C21: 0.055 | D21: de los ingresos
B22: Costo de materia prima | C22: 1600000 | D22: la tonelada
B23: Crecimiento real materia prima | C23: 0.02
B24: Renovación (overhaul) AÑO 5 | C24: 0.7 | D24: del valor inicial de la adquisición | E24: Pagina 5 Nota 13
B25: Porcentaje de seguro | C25: 0.1 | D25: sobre el valor inicial de los activos | E25: Pagina 6
B26: Gastos operacionales variables | C26: 0.25 | D26: sobre los ingresos
B27: Comisiones | C27: 0.02 | D27: sobre los ingresos
B28: CXC (días) | C28: 30 | E28: Pagina 7
B29: CXP (días) | C29: 90
B30: Precio de venta | C30: 6500000 | D30: millones
B31: Crecimiento real anual | C31: 0.06
B32: Política de crédito sugerido por área comercial | C32: 120 | D32: días en vez de 95
B33: Aumento esperado en ventas atado a la política sugerida | C33: 0.02
B34: %E | C34: 0.4 | D34: porcentaje de equity
B35: %D | C35: 0.6 | D35: porcentaje de deuda
B36: Política de dividendos | C36: 0.9

Sheet Nómina
A2: Cargo | B2: No | C2: Salario / Mes (millones de COP) | D2: Salario anual (millones de COP) | E2: ¿Es parte de la producción?
A3: Gerente del Proyecto | B3: 1 | C3: 15 | D3: =C3*12*B3 -> 180 | E3: NO | G3: Salario anual de nómina operativa | H3: =SUMIF(E3:E17,"SI",D3:D17)*1000000 -> 300000000 | I3: millones de COP
A4: Jefe de Producción | B4: 1 | C4: 9.5 | D4: =C4*12*B4 -> 114 | E4: SI | G4: Salario anual de nómina administrativa | H4: =SUMIF(E3:E17,"NO",D3:D17)*1000000 -> 1488000000 | I4: millones de COP
A5: Secretaria | B5: 1 | C5: 3.5 | D5: =C5*12*B5 -> 42 | E5: NO
A6: Director Financiero | B6: 1 | C6: 15 | D6: =C6*12*B6 -> 180 | E6: NO
A7: Director de Gestión Humana | B7: 1 | C7: 12 | D7: =C7*12*B7 -> 144 | E7: NO
A8: Contador | B8: 1 | C8: 10 | D8: =C8*12*B8 -> 120 | E8: NO
A9: Ingeniero de mantenimiento | B9: 1 | C9: 7.5 | D9: =C9*12*B9 -> 90 | E9: SI
A10: Analista de Gestión Humana | B10: 1 | C10: 4 | D10: =C10*12*B10 -> 48 | E10: NO
A11: Auxiliares operativos | B11: 2 | C11: 4 | D11: =C11*12*B11 -> 96 | E11: SI
A12: Auxiliar administrativo | B12: 1 | C12: 4 | D12: =C12*12*B12 -> 48 | E12: NO
A13: Auxiliar contable | B13: 1 | C13: 3.5 | D13: =C13*12*B13 -> 42 | E13: NO
A14: Jefe de Salud y Seguridad en el trabajo | B14: 1 | C14: 8 | D14: =C14*12*B14 -> 96 | E14: NO
A15: Auxiliar Salud y Seguridad en el trabajo | B15: 1 | C15: 4 | D15: =C15*12*B15 -> 48 | E15: NO
A16: Asesores comerciales | B16: 5 | C16: 7 | D16: =C16*12*B16 -> 420 | E16: NO
A17: Personal de vigilancia | B17: 4 | C17: 2.5 | D17: =C17*12*B17 -> 120 | E17: NO
A18: Total | B18: =SUM(B3:B17) -> 23 | C18: =SUM(C3:C17) -> 109.5 | D18: =SUM(D3:D17) -> 1788
A20: Factor salarial | B20: 4.5
A22: Nota: este factor salarial se usa para saber cuánto cobrarle al cliente por hora/mes de un profesional, como no estamos vendiendo tiempo de personas y estamos vendiendo toneladas de aluminio, este valor no aplica
A24: Pagina 6_Nota 15 = Incremento salarial con base en la inflación al cierre del año inmediatamente anterior

Sheet Costo de oportunidad
A4: Mantenimiento de bodega | B4: 0.03
A5: Multa por quitar arrendadores
B7: Año 1 | C7: Año 2 | D7: Año 3 | E7: Año 4 | F7: Año 5 | G7: Año 6 | H7: Año 7 | I7: Año 8 | J7: Año 9 | K7: Año 10
A8: Consecutivo | B8: 1 | C8: 2 | D8: 3 | E8: 4 | F8: 5 | G8: 6 | H8: 7 | I8: 8 | J8: 9 | K8: 10
A9: Inflación | B9: 0.064 | C9: 0.037 | D9: 0.03525 | E9: 0.0335 | F9: 0.03175 | G9: 0.03 | H9: 0.037071068 | I9: 0.04 | J9: 0.037071068 | K9: 0.03
A10: Canón | B10: =Datos!C19*1000000 -> 2800000000 | C10: =B10*(1+B9) -> 2979200000 | D10: =C10*(1+C9) -> 3089430400 | E10: =D10*(1+D9) -> 3.1983328e+09 | F10: =E10*(1+E9) -> 3.305477e+09 | G10: =F10*(1+F9) -> 3.4104259e+09 | H10: =G10*(1+G9) -> 3.5127386e+09 | I10: =H10*(1+H9) -> 3.6429596e+09 | J10: =I10*(1+I9) -> 3.788678e+09 | K10: =J10*(1+J9) -> 3.9291283e+09
B11: =B10*$B$4 -> 84000000 | C11: =C10*$B$4 -> 89376000 | D11: =D10*$B$4 -> 92682912 | E11: =E10*$B$4 -> 95949985 | F11: =F10*$B$4 -> 99164309 | G11: =G10*$B$4 -> 1.0231278e+08 | H11: =H10*$B$4 -> 1.0538216e+08 | I11: =I10*$B$4 -> 1.0928879e+08 | ... K11: =K10*$B$4 -> 1.1787385e+08
A12: Flujo de caja | B12: =B10-B11 -> 2716000000 | C12: =C10-C11 -> 2889824000 | D12: =D10-D11 -> 2996747488 | E12: =E10-E11 -> 3.1023828e+09 | F12: =F10-F11 -> 3.2063127e+09 | G12: =G10-G11 -> 3.3081131e+09 | H12: =H10-H11 -> 3.4073565e+09 | I12: =I10-I11 -> 3.5336708e+09 | ... K12: =K10-K11 -> 3.8112545e+09
A13: Factor de descuento | B13: =1/(1+B9)^B8 -> 0.93984962 | C13: =1/(1+C9)^C8 -> 0.92991336 | D13: =1/(1+D9)^D8 -> 0.90128944 | E13: =1/(1+E9)^E8 -> 0.87651242 | F13: =1/(1+F9)^F8 -> 0.855318 | G13: =1/(1+G9)^G8 -> 0.83748426 | H13: =1/(1+H9)^H8 -> 0.77506901 | I13: =1/(1+I9)^I8 -> 0.73069021 | ... K13: =1/(1+K9)^K8 -> 0.74409391
A14: Flujo de caja descontado | B14: =B12*B13 -> 2.5526316e+09 | C14: =C12*C13 -> 2.6872859e+09 | D14: =D12*D13 -> 2.7009369e+09 | E14: =E12*E13 -> 2.7192771e+09 | F14: =F12*F13 -> 2.7424169e+09 | G14: =G12*G13 -> 2.7704926e+09 | H14: =H12*H13 -> 2.6409364e+09 | I14: =I12*I13 -> 2.5820187e+09 | ... K14: =K12*K13 -> 2.8359313e+09
A16: Valor presente | B16: =SUM(B14:K14) -> 2.6880322e+10

Sheet Costos hundidos
B2: Estudio de mercado | C2: 5000 | D2: millones (COP)
B3: Estudios técnicos | C3: 2500 | D3: millones (COP)
B4: Avalúo comercial | C4: 420 | D4: millones (COP)
B6: Total | C6: =SUM(C2:C4) -> 7920 | D6: millones (COP)

Sheet Tasas de banco
E2: Datos | F2: Fuente
A3: Banco de Bogotá | D3: DTF TA | E3: 0.0848 | F3: https://www.grupoaval.com/wps/portal/grupo-aval/aval/portal-financiero/indicadores/tasas-interes
A4: Plazo 10 años | D4: Tasa TA | E4: 0.1898
A5: Tasa (DTF + 10.5% TA) | D5: Período trimestre anticipado | E5: 0.0475
A6: Pago de interés trimestral | D6: Período trimestre vencido | E6: 0.0498
A7: Amortización | D7: Nominal anual trimestre vencido | E7: 0.1993
A8: 1 año de gracia para pago de capital | D8: Efectivo anual | E8: 0.2147
A9: Amortizaciones de capitales anuales (10% a partir del año 2 y 20% al vencimiento)
A10: Gastos iniciales (6% sobre el valor del crédito descontado del valor desembolsado)
A12: Banco BBVA | E12: Datos | F12: Fuente
A13: Plazo 10 años | D13: IBR | E13: 0.10516 | F13: https://www.banrep.gov.co/es/glosario/indicador-bancario-referencia-ibr
A14: Tasa (IBR + 10.5% TV) | D14: Tasa TV (IBR + 10,5%) | E14: =+E13+10.5% -> 0.21016
A15: Pago de intereses trimestral | D15: Período trimestre vencido | E15: =+E14/4 -> 0.05254
A16: Pago: cuota fija (2 años de gracia de pago de capital) | D16: Nominal anual trimestre vencido | E16: =+E13+10.5% -> 0.21016
A17: Gastos iniciales (5.5% sobre el valor del crédito descontado del valor desembolsado) | D17: Efectivo anual | E17: =(1+E15)^4-1 -> 0.22731047
A19: Emisión de bonos corporativos
A20: Plazo 10 años
A21: Tasa: IPC + 10.5 E.A.
A22: Pago intereses: semestral
A23: Pago de capital: al vencimiento (bullet)
A24: Gastos emisión y estructuración (25% sobre el valor de emisión)
A26: ESTRUCTURA DE CAPITAL BASE
A27: Concepto | B27: Valor
A28: Inversión Total | B28: =+Datos!C10+Datos!C15 -> 21920
A29: % Deuda | B29: 0.1
A30: Valor Crédito | B30: =+B28*B29 -> 2192
A32: Concepto | B32: Banco Bogotá | C32: BBVA | D32: Bonos
A33: Plazo (años) | B33: 10 | C33: 10 | D33: 10
A34: Tasa base | B34: DTF+10.5% | C34: IBR+10.5% | D34: IPC+10.5%
A35: EA equivalente | B35: =+E8 -> 0.2147 | C35: =+E17 -> 0.22731047 | D35: X
A36: Pago intereses | B36: Trimestral | C36: Trimestral | D36: Semestral
A37: Gracia capital | B37: 1 año | C37: 2 años | D37: No aplica
A38: Forma pago capital | B38: Amortización | C38: Cuota fija | D38: Bullet
A39: Gastos iniciales | B39: 0.06 | C39: 5,5% | D39: 0.25
A40: Desembolso neto
A41: Intereses totales
A42: Costo efectivo
A44: BANCO DE BOGOTA
A45: Período | B45: Fecha | C45: Saldo Inicial | D45: Interés | E45: Capital | F45: Cuota | G45: Saldo Final
A46: 0 | B46: 46023 | C46: =+B30 -> 2192 | E46: =+IF(OR(A46=8,A46=12,A46=16,A46=20,A46=24,A46=28,A46=32,A46=36),14000000,IF(A46=40,14000000,0)) -> 0 | F46: =+D46+E46 -> 0 | G46: =+C46 -> 2192
A47: 1 | B47: =EDATE(B46,3) -> 46113 | G47: =+C47-E47 -> 0
A48: 2 | B48: =EDATE(B47,3) -> 46204 | G48: =+C48-E48 -> 0
A49: 3 | B49: =EDATE(B48,3) -> 46296 | G49: =+C49-E49 -> 0
A50: 4 | B50: =EDATE(B49,3) -> 46388 | G50: =+C50-E50 -> 0
A51: 5 | B51: =EDATE(B50,3) -> 46478 | G51: =+C51-E51 -> 0
A52: 6 | B52: =EDATE(B51,3) -> 46569 | G52: =+C52-E52 -> 0
A53: 7 | B53: =EDATE(B52,3) -> 46661 | G53: =+C53-E53 -> 0
A54: 8 | B54: =EDATE(B53,3) -> 46753 | G54: =+C54-E54 -> 0
A55: 9 | B55: =EDATE(B54,3) -> 46844 | G55: =+C55-E55 -> 0
A56: 10 | B56: =EDATE(B55,3) -> 46935 | G56: =+C56-E56 -> 0
A57: 11 | B57: =EDATE(B56,3) -> 47027 | G57: =+C57-E57 -> 0
A58: 12 | B58: =EDATE(B57,3) -> 47119 | G58: =+C58-E58 -> 0
... A86: 40 | B86: =EDATE(B85,3) -> 49675 | G86: =+C86-E86 -> 0

Sheet Inflación
A1: Proyección de Inflación Colombia a 10 Años (2026-2035)
A3: Párametro | B3: Fecha | C3: Fuente
A4: Tes TF | B4: 46188 | C4: https://www.grupoaval.com/wps/portal/grupo-aval/aval/portal-financiero/renta-fija/tes/curva-rentabilidad
A5: Tes UVR | B5: 46188 | C5: 1. https://www.grupoaval.com/wps/portal/grupo-aval/aval/portal-financiero/renta-fija/tes/datos-historicos
C6: 2. https://www.bvc.com.co/renta-fija-deuda-publica-segmento-publico/tuvt11170327?tab=resumen
C7: 3. https://www.irc.gov.co/440
A10: Año | B10: Tes TF | C10: Tes UVR | D10: Inflación proyectada
A11: 2026 | D11: 0.0584
A12: 2027 | B12: 0.1303 | C12: 0.0619 | D12: =B12-C12 -> 0.0684
A13: 2028 | B13: 0.1299 | C13: =AVERAGE(C12,C14) -> 0.0641 | D13: =B13-C13 -> 0.0658
A14: 2029 | B14: 0.13 | C14: 0.0663 | D14: =B14-C14 -> 0.0637
A15: 2030 | B15: 0.1299 | C15: =AVERAGE(C14,C16) -> 0.06815 | D15: =B15-C15 -> 0.06175
A16: 2031 | B16: 0.1285 | C16: 0.07 | D16: =B16-C16 -> 0.0585
A17: 2032 | B17: 0.1265 | C17: =AVERAGE(C16,C18) -> 0.06835 | D17: =B17-C17 -> 0.05815
A18: 2033 | B18: 0.1255 | C18: 0.0667 | D18: =B18-C18 -> 0.0588
A19: 2034 | B19: 0.1247 | C19: =AVERAGE(C18,C20) -> 0.0661 | D19: =B19-C19 -> 0.0586
A20: 2035 | B20: 0.124 | C20: 0.0655 | D20: =B20-C20 -> 0.0585
A22: Nota: para el año 2026 se trabaja con la inflación reportada en mayo del 2026, para los años 2028, 2030, 2032 y 2034
A23: se hace una interpolación simple con respecto al año anterior y siguiente.
A34: Fuente: https://www.irc.gov.co/440

Sheet Bancos
A1: TABLA DE AMORTIZACIÓN - BANCO DE BOGOTÁ | P1: TABLA DE AMORTIZACIÓN - BANCO BBVA
A3: PARÁMETROS DEL PRÉSTAMO | D3: NOTAS: | P3: PARÁMETROS DEL PRÉSTAMO | S3: NOTAS:
A4: DTF (T.A.) - Vigente Jun 2026 | B4: 0.0936 | D4: DTF vigente 8-14 Jun 2026: 9.36% T.A. (Fuente: Banco de la República) | P4: IBR (T.V.) - Vigente Jun 2026 | Q4: 0.09 | S4: IBR vigente (~9.0% T.V.) | AF4: Plazo | AG4: 10 años
A5: Spread Banco Bogotá (T.A.) | B5: 0.105 | D5: Tasa Anticipada (TA) convertida a Vencida para cálculo de intereses | P5: Spread Banco BBVA (T.V.) | Q5: 0.105 | S5: Spread 10.5% Tasa Vencida | AF5: Tasa | AG5: IPC + 10,5% E.A.
A6: Tasa Total (T.A.) | B6: =B4+B5 -> 0.1986 | D6: Año 1: Período de gracia para capital (solo se pagan intereses) | P6: Tasa Total (T.V.) | Q6: =Q4+Q5 -> 0.195 | S6: IBR + Spread = Tasa nominal anual vencida | AF6: Spread | AG6: 0.105
A7: Tasa Trimestral Anticipada | B7: =(B6/4) -> 0.04965 | D7: Años 2-9: Amortización 10% anual del capital (2.5% trimestral) | P7: n1 | Q7: =360/92 -> 3.9130435 | AF7: IPC | AG7: 0.064
A8: Tasa Trimestral Vencido | B8: =B7/(1-B7) -> 0.05224391 | D8: Año 10: Amortización 20% anual del capital (5% trimestral) | P8: n2 | Q8: =365/92 -> 3.9673913 | AF8: Tasa Efectiva Anual | AG8: =AG6+AG7 -> 0.169
A9: Nominal Anual Trimestre Vencido | B9: =B8*4 -> 0.20897564 | D9: https://suameca.banrep.gov.co/indicadores-economicos-del-dia/ | P9: Tasa Trimestral Efectiva | Q9: =Q6/Q7 -> 0.049833333 | S9: Tasa trimestral para cálculo de intereses | AF9: Tasa Efectivo Semestral | AG9: =(1+AG8)^(6/12)-1 -> 0.081203034
A10: Efectivo Anual | B10: =(1+B9/4)^4-1 -> 0.22593003 | P10: Tasa Efectiva Anual | Q10: =(1+Q9)^Q8-1 -> 0.21280988 | S10: TEA calculada | AF10: Monto del Crédito (asumido) | AG10: =+B12 -> 8400
A11: Plazo (años) | B11: 10 | P11: Plazo (años) | Q11: 10 | S11: 10 años plazo total | AF11: Gastos (porcentaje) | AG11: 0.25
A12: Monto del Crédito (asumido) | B12: =Datos!C10*Datos!C35 -> 8400 | P12: Monto del Crédito | Q12: =+B12 -> 8400 | S12: Vinculado al monto de bogota | AF12: Gastos | AG12: =AG10*AG11 -> 2100
A13: Gastos Iniciales (%) | B13: 0.06 | P13: Gastos Iniciales (%) | Q13: 0.055 | S13: 5.5% sobre el valor del crédito | AF13: Intereses | AG13: =AG9*AG10 -> 682.10548 | AM13: RESUMEN ANUAL
A14: Valor Gastos Iniciales | B14: =B12*B13 -> 504 | P14: Valor Gastos Iniciales | Q14: =Q12*Q13 -> 462 | S14: Descontado del desembolso
A15: Monto Neto Desembolsado | B15: =B12-B14 -> 7896 | P15: Monto Neto Desembolsado | Q15: =Q12-Q14 -> 7938 | AM15: Año | AN15: Cupones | AO15: Amort. Principal | AP15: Pago Total | AQ15: Saldo Final
A16: Kd_DI | B16: =B10*(1-0.35) -> 0.14685452 | P16: Período de Gracia (años) | Q16: 2 | S16: Solo pago de intereses años 1-2 | AM16: 1 | AN16: =SUMIF($AG$20:$AG$39,AM16,$AI$20:$AI$39) -> 1364.211 | AO16: =SUMIF($AG$20:$AG$39,AM16,$AJ$20:$AJ$39) -> 0 | AP16: =+AN16+AO16 -> 1364.211
A17: TABLA DE AMORTIZACIÓN TRIMESTRAL | I17: RESUMEN ANUAL | P17: Cuota Fija Trimestral (Años 3-10) | Q17: =PMT(Q9,32,-Q12) -> 530.50126 | S17: Cuota fija para años 3-10 (32 trimestres) | AM17: 2 | AN17: =SUMIF($AG$20:$AG$39,AM17,$AI$20:$AI$39) -> 1364.211 | AO17: =SUMIF($AG$20:$AG$39,AM17,$AJ$20:$AJ$39) -> 0 | AP17: =+AN17+AO17 -> 1364.211
AM18: 3 | AN18: =SUMIF($AG$20:$AG$39,AM18,$AI$20:$AI$39) -> 1364.211 | AO18: =SUMIF($AG$20:$AG$39,AM18,$AJ$20:$AJ$39) -> 0 | AP18: =+AN18+AO18 -> 1364.211
A19: Trimestre | B19: Año | C19: Saldo Inicial | D19: Interés Trimestral | E19: Amort. Capital | F19: Pago Total | G19: Saldo Final | I19: Año | J19: Intereses | K19: Amort. Capital | L19: Pago Total | M19: Saldo Final | P19: TABLA DE AMORTIZACIÓN TRIMESTRAL | X19: RESUMEN ANUAL | AF19: Semestre | AG19: Año | AH19: Capital | AI19: Cupón (Interés) | AJ19: Amortización | AK19: Flujo Total | AM19: 4 | AN19: =SUMIF($AG$20:$AG$39,AM19,$AI$20:$AI$39) -> 1364.211 | AO19: =SUMIF($AG$20:$AG$39,AM19,$AJ$20:$AJ$39) -> 0 | AP19: =+AN19+AO19 -> 1364.211
A20: 1 | B20: 1 | C20: =$B$12 -> 8400 | D20: =C20*$B$8 -> 438.84885 | E20: =IF(B20=1,0,IF(B20<10,$B$12*0.1/4,$B$12*0.2/4)) -> 0 | F20: =D20+E20 -> 438.84885 | G20: =C20-E20 -> 8400 | I20: 1 | J20: =SUM(D20:D23) -> 1755.3954 | K20: =SUM(E20:E23) -> 0 | L20: =SUM(F20:F23) -> 1755.3954 | M20: =G23 -> 8400 | AF20: 1 | AG20: 1 | AH20: =+$AG$10 -> 8400 | AI20: =+$AG$13 -> 682.10548 | AJ20: 0 | AK20: =+AI20+AJ20 -> 682.10548 | AM20: 5 | AN20: =SUMIF($AG$20:$AG$39,AM20,$AI$20:$AI$39) -> 1364.211 | AO20: =SUMIF($AG$20:$AG$39,AM20,$AJ$20:$AJ$39) -> 0 | AP20: =+AN20+AO20 -> 1364.211
A21: 2 | B21: 1 | C21: =G20 -> 8400 | D21: =C21*$B$8 -> 438.84885 | E21: =IF(B21=1,0,IF(B21<10,$B$12*0.1/4,$B$12*0.2/4)) -> 0 | F21: =D21+E21 -> 438.84885 | G21: =C21-E21 -> 8400 | I21: 2 | J21: =SUM(D24:D27) -> 1689.5681 | K21: =SUM(E24:E27) -> 840 | L21: =SUM(F24:F27) -> 2529.5681 | M21: =G27 -> 7560 | P21: Trimestre | Q21: Año | R21: Saldo Inicial | S21: Interés Trimestral | T21: Amort. Capital | U21: Pago Total | V21: Saldo Final | X21: Año | Y21: Intereses | Z21: Amort. Capital | AA21: Pago Total | AB21: Saldo Final | AF21: 2 | AG21: 1 | AH21: =+$AG$10 -> 8400 | AI21: =+$AG$13 -> 682.10548 | AJ21: 0 | AK21: =+AI21+AJ21 -> 682.10548 | AM21: 6 | AN21: =SUMIF($AG$20:$AG$39,AM21,$AI$20:$AI$39) -> 1364.211 | AO21: =SUMIF($AG$20:$AG$39,AM21,$AJ$20:$AJ$39) -> 0 | AP21: =+AN21+AO21 -> 1364.211
A22: 3 | B22: 1 | C22: =G21 -> 8400 | D22: =C22*$B$8 -> 438.84885 | E22: =IF(B22=1,0,IF(B22<10,$B$12*0.1/4,$B$12*0.2/4)) -> 0 | F22: =D22+E22 -> 438.84885 | G22: =C22-E22 -> 8400 | I22: 3 | J22: =SUM(D28:D31) -> 1514.0285 | K22: =SUM(E28:E31) -> 840 | L22: =SUM(F28:F31) -> 2354.0285 | M22: =G31 -> 6720 | P22: 1 | Q22: =CEILING(P22/4,1) -> 1 | R22: =$B$12 -> 8400 | S22: =R22*$Q$9 -> 418.6 | T22: =IF(Q22<=$Q$16,0,$Q$17-S22) -> 0 | U22: =S22+T22 -> 418.6 | V22: =R22-T22 -> 8400 | X22: 1 | Y22: =SUMIF($B$22:$B$61,X22,$D$22:$D$61) -> 877.69769 | Z22: =SUMIF($B$22:$B$61,X22,$E$22:$E$61) -> 0 | AA22: =SUMIF($B$22:$B$61,X22,$F$22:$F$61) -> 877.69769 | AB22: {=INDEX($G$22:$G$61,X22*4)} -> 7980 | AF22: 3 | AG22: 2 | AH22: =+$AG$10 -> 8400 | AI22: =+$AG$13 -> 682.10548 | AJ22: 0 | AK22: =+AI22+AJ22 -> 682.10548 | AM22: 7 | AN22: =SUMIF($AG$20:$AG$39,AM22,$AI$20:$AI$39) -> 1364.211 | AO22: =SUMIF($AG$20:$AG$39,AM22,$AJ$20:$AJ$39) -> 0 | AP22: =+AN22+AO22 -> 1364.211
A23: 4 | B23: 1 | C23: =G22 -> 8400 | D23: =C23*$B$8 -> 438.84885 | E23: =IF(B23=1,0,IF(B23<10,$B$12*0.1/4,$B$12*0.2/4)) -> 0 | F23: =D23+E23 -> 438.84885 | G23: =C23-E23 -> 8400 | I23: 4 | J23: =SUM(D32:D35) -> 1338.489 | K23: =SUM(E32:E35) -> 840 | L23: =SUM(F32:F35) -> 2178.489 | M23: =G35 -> 5880 | P23: 2 | Q23: =CEILING(P23/4,1) -> 1 | R23: =V22 -> 8400 | S23: =R23*$Q$9 -> 418.6 | T23: =IF(Q23<=$Q$16,0,$Q$17-S23) -> 0 | U23: =S23+T23 -> 418.6 | V23: =R23-T23 -> 8400 | X23: 2 | Y23: =SUMIF($B$22:$B$61,X23,$D$22:$D$61) -> 1689.5681 | Z23: =SUMIF($B$22:$B$61,X23,$E$22:$E$61) -> 840 | AA23: =SUMIF($B$22:$B$61,X23,$F$22:$F$61) -> 2529.5681 | AB23: {=INDEX($G$22:$G$61,X23*4)} -> 7140 | AF23: 4 | AG23: 2 | AH23: =+$AG$10 -> 8400 | AI23: =+$AG$13 -> 682.10548 | AJ23: 0 | AK23: =+AI23+AJ23 -> 682.10548 | AM23: 8 | AN23: =SUMIF($AG$20:$AG$39,AM23,$AI$20:$AI$39) -> 1364.211 | AO23: =SUMIF($AG$20:$AG$39,AM23,$AJ$20:$AJ$39) -> 0 | AP23: =+AN23+AO23 -> 1364.211
A24: 5 | B24: 2 | C24: =G23 -> 8400 | D24: =C24*$B$8 -> 438.84885 | E24: =IF(B24=1,0,IF(B24<10,$B$12*0.1/4,$B$12*0.2/4)) -> 210 | F24: =D24+E24 -> 648.84885 | G24: =C24-E24 -> 8190 | I24: 5 | J24: =SUM(D36:D39) -> 1162.9494 | K24: =SUM(E36:E39) -> 840 | L24: =SUM(F36:F39) -> 2002.9494 | M24: =G39 -> 5040 | P24: 3 | Q24: =CEILING(P24/4,1) -> 1 | R24: =V23 -> 8400 | S24: =R24*$Q$9 -> 418.6 | T24: =IF(Q24<=$Q$16,0,$Q$17-S24) -> 0 | U24: =S24+T24 -> 418.6 | V24: =R24-T24 -> 8400 | X24: 3 | Y24: =SUMIF($B$22:$B$61,X24,$D$22:$D$61) -> 1514.0285 | Z24: =SUMIF($B$22:$B$61,X24,$E$22:$E$61) -> 840 | AA24: =SUMIF($B$22:$B$61,X24,$F$22:$F$61) -> 2354.0285 | AB24: {=INDEX($G$22:$G$61,X24*4)} -> 6300 | AF24: 5 | AG24: 3 | AH24: =+$AG$10 -> 8400 | AI24: =+$AG$13 -> 682.10548 | AJ24: 0 | AK24: =+AI24+AJ24 -> 682.10548 | AM24: 9 | AN24: =SUMIF($AG$20:$AG$39,AM24,$AI$20:$AI$39) -> 1364.211 | AO24: =SUMIF($AG$20:$AG$39,AM24,$AJ$20:$AJ$39) -> 0 | AP24: =+AN24+AO24 -> 1364.211
A25: 6 | B25: 2 | C25: =G24 -> 8190 | D25: =C25*$B$8 -> 427.87762 | E25: =IF(B25=1,0,IF(B25<10,$B$12*0.1/4,$B$12*0.2/4)) -> 210 | F25: =D25+E25 -> 637.87762 | G25: =C25-E25 -> 7980 | I25: 6 | J25: =SUM(D40:D43) -> 987.4099 | K25: =SUM(E40:E43) -> 840 | L25: =SUM(F40:F43) -> 1827.4099 | M25: =G43 -> 4200 | P25: 4 | Q25: =CEILING(P25/4,1) -> 1 | R25: =V24 -> 8400 | S25: =R25*$Q$9 -> 418.6 | T25: =IF(Q25<=$Q$16,0,$Q$17-S25) -> 0 | U25: =S25+T25 -> 418.6 | V25: =R25-T25 -> 8400 | X25: 4 | Y25: =SUMIF($B$22:$B$61,X25,$D$22:$D$61) -> 1338.489 | Z25: =SUMIF($B$22:$B$61,X25,$E$22:$E$61) -> 840 | AA25: =SUMIF($B$22:$B$61,X25,$F$22:$F$61) -> 2178.489 | AB25: {=INDEX($G$22:$G$61,X25*4)} -> 5460 | AF25: 6 | AG25: 3 | AH25: =+$AG$10 -> 8400 | AI25: =+$AG$13 -> 682.10548 | AJ25: 0 | AK25: =+AI25+AJ25 -> 682.10548 | AM25: 10 | AN25: =SUMIF($AG$20:$AG$39,AM25,$AI$20:$AI$39) -> 1364.211 | AO25: =SUMIF($AG$20:$AG$39,AM25,$AJ$20:$AJ$39) -> 8400 | AP25: =+AN25+AO25 -> 9764.211
A26: 7 | B26: 2 | C26: =G25 -> 7980 | D26: =C26*$B$8 -> 416.9064 | E26: =IF(B26=1,0,IF(B26<10,$B$12*0.1/4,$B$12*0.2/4)) -> 210 | F26: =D26+E26 -> 626.9064 | G26: =C26-E26 -> 7770 | I26: 7 | J26: =SUM(D44:D47) -> 811.87036 | K26: =SUM(E44:E47) -> 840 | L26: =SUM(F44:F47) -> 1651.8704 | M26: =G47 -> 3360 | P26: 5 | Q26: =CEILING(P26/4,1) -> 2 | R26: =V25 -> 8400 | S26: =R26*$Q$9 -> 418.6 | T26: =IF(Q26<=$Q$16,0,$Q$17-S26) -> 0 | U26: =S26+T26 -> 418.6 | V26: =R26-T26 -> 8400 | X26: 5 | Y26: =SUMIF($B$22:$B$61,X26,$D$22:$D$61) -> 1162.9494 | Z26: =SUMIF($B$22:$B$61,X26,$E$22:$E$61) -> 840 | AA26: =SUMIF($B$22:$B$61,X26,$F$22:$F$61) -> 2002.9494 | AB26: {=INDEX($G$22:$G$61,X26*4)} -> 4620 | AF26: 7 | AG26: 4 | AH26: =+$AG$10 -> 8400 | AI26: =+$AG$13 -> 682.10548 | AJ26: 0 | AK26: =+AI26+AJ26 -> 682.10548 | AM26: TOTAL | AN26: =SUM(AN16:AN25) -> 13642.11 | AO26: =SUM(AO16:AO25) -> 8400 | AP26: =SUM(AP16:AP25) -> 22042.11
A27: 8 | B27: 2 | C27: =G26 -> 7770 | D27: =C27*$B$8 -> 405.93518 | E27: =IF(B27=1,0,IF(B27<10,$B$12*0.1/4,$B$12*0.2/4)) -> 210 | F27: =D27+E27 -> 615.93518 | G27: =C27-E27 -> 7560 | I27: 8 | J27: =SUM(D48:D51) -> 636.33083 | K27: =SUM(E48:E51) -> 840 | L27: =SUM(F48:F51) -> 1476.3308 | M27: =G51 -> 2520 | P27: 6 | Q27: =CEILING(P27/4,1) -> 2 | R27: =V26 -> 8400 | S27: =R27*$Q$9 -> 418.6 | T27: =IF(Q27<=$Q$16,0,$Q$17-S27) -> 0 | U27: =S27+T27 -> 418.6 | V27: =R27-T27 -> 8400 | X27: 6 | Y27: =SUMIF($B$22:$B$61,X27,$D$22:$D$61) -> 987.4099 | Z27: =SUMIF($B$22:$B$61,X27,$E$22:$E$61) -> 840 | AA27: =SUMIF($B$22:$B$61,X27,$F$22:$F$61) -> 1827.4099 | AB27: {=INDEX($G$22:$G$61,X27*4)} -> 3780 | AF27: 8 | AG27: 4 | AH27: =+$AG$10 -> 8400 | AI27: =+$AG$13 -> 682.10548 | AJ27: 0 | AK27: =+AI27+AJ27 -> 682.10548
A28: 9 | B28: 3 | C28: =G27 -> 7560 | D28: =C28*$B$8 -> 394.96396 | E28: =IF(B28=1,0,IF(B28<10,$B$12*0.1/4,$B$12*0.2/4)) -> 210 | F28: =D28+E28 -> 604.96396 | G28: =C28-E28 -> 7350 | I28: 9 | J28: =SUM(D52:D55) -> 460.79129 | K28: =SUM(E52:E55) -> 840 | L28: =SUM(F52:F55) -> 1300.7913 | M28: =G55 -> 1680 | P28: 7 | Q28: =CEILING(P28/4,1) -> 2 | R28: =V27 -> 8400 | S28: =R28*$Q$9 -> 418.6 | T28: =IF(Q28<=$Q$16,0,$Q$17-S28) -> 0 | U28: =S28+T28 -> 418.6 | V28: =R28-T28 -> 8400 | X28: 7 | Y28: =SUMIF($B$22:$B$61,X28,$D$22:$D$61) -> 811.87036 | Z28: =SUMIF($B$22:$B$61,X28,$E$22:$E$61) -> 840 | AA28: =SUMIF($B$22:$B$61,X28,$F$22:$F$61) -> 1651.8704 | AB28: {=INDEX($G$22:$G$61,X28*4)} -> 2940 | AF28: 9 | AG28: 5 | AH28: =+$AG$10 -> 8400 | AI28: =+$AG$13 -> 682.10548 | AJ28: 0 | AK28: =+AI28+AJ28 -> 682.10548
A29: 10 | B29: 3 | C29: =G28 -> 7350 | D29: =C29*$B$8 -> 383.99274 | E29: =IF(B29=1,0,IF(B29<10,$B$12*0.1/4,$B$12*0.2/4)) -> 210 | F29: =D29+E29 -> 593.99274 | G29: =C29-E29 -> 7140 | I29: 10 | J29: =SUM(D56:D59) -> 219.42442 | K29: =SUM(E56:E59) -> 1680 | L29: =SUM(F56:F59) -> 1899.4244 | M29: =G59 -> 0 | P29: 8 | Q29: =CEILING(P29/4,1) -> 2 | R29: =V28 -> 8400 | S29: =R29*$Q$9 -> 418.6 | T29: =IF(Q29<=$Q$16,0,$Q$17-S29) -> 0 | U29: =S29+T29 -> 418.6 | V29: =R29-T29 -> 8400 | X29: 8 | Y29: =SUMIF($B$22:$B$61,X29,$D$22:$D$61) -> 636.33083 | Z29: =SUMIF($B$22:$B$61,X29,$E$22:$E$61) -> 840 | AA29: =SUMIF($B$22:$B$61,X29,$F$22:$F$61) -> 1476.3308 | AB29: {=INDEX($G$22:$G$61,X29*4)} -> 2100 | AF29: 10 | AG29: 5 | AH29: =+$AG$10 -> 8400 | AI29: =+$AG$13 -> 682.10548 | AJ29: 0 | AK29: =+AI29+AJ29 -> 682.10548
A30: 11 | B30: 3 | C30: =G29 -> 7140 | D30: =C30*$B$8 -> 373.02152 | E30: =IF(B30=1,0,IF(B30<10,$B$12*0.1/4,$B$12*0.2/4)) -> 210 | F30: =D30+E30 -> 583.02152 | G30: =C30-E30 -> 6930 | I30: TOTAL | J30: =SUM(J20:J29) -> 10576.257 | K30: =SUM(K20:K29) -> 8400 | L30: =SUM(L20:L29) -> 18976.257 | P30: 9 | Q30: =CEILING(P30/4,1) -> 3 | R30: =V29 -> 8400 | S30: =R30*$Q$9 -> 418.6 | T30: =IF(Q30<=$Q$16,0,$Q$17-S30) -> 111.90126 | U30: =S30+T30 -> 530.50126 | V30: =R30-T30 -> 8288.0987 | X30: 9 | Y30: =SUMIF($B$22:$B$61,X30,$D$22:$D$61) -> 460.79129 | Z30: =SUMIF($B$22:$B$61,X30,$E$22:$E$61) -> 840 | AA30: =SUMIF($B$22:$B$61,X30,$F$22:$F$61) -> 1300.7913 | AB30: {=INDEX($G$22:$G$61,X30*4)} -> 840 | AF30: 11 | AG30: 6 | AH30: =+$AG$10 -> 8400 | AI30: =+$AG$13 -> 682.10548 | AJ30: 0 | AK30: =+AI30+AJ30 -> 682.10548
A31: 12 | B31: 3 | C31: =G30 -> 6930 | D31: =C31*$B$8 -> 362.0503 | E31: =IF(B31=1,0,IF(B31<10,$B$12*0.1/4,$B$12*0.2/4)) -> 210 | F31: =D31+E31 -> 572.0503 | G31: =C31-E31 -> 6720 | P31: 10 | Q31: =CEILING(P31/4,1) -> 3 | R31: =V30 -> 8288.0987 | S31: =R31*$Q$9 -> 413.02359 | T31: =IF(Q31<=$Q$16,0,$Q$17-S31) -> 117.47767 | U31: =S31+T31 -> 530.50126 | V31: =R31-T31 -> 8170.6211 | X31: 10 | Y31: =SUMIF($B$22:$B$61,X31,$D$22:$D$61) -> 219.42442 | Z31: =SUMIF($B$22:$B$61,X31,$E$22:$E$61) -> 1680 | AA31: =SUMIF($B$22:$B$61,X31,$F$22:$F$61) -> 1899.4244 | AB31: {=INDEX($G$22:$G$61,X31*4)} -> 0 | AF31: 12 | AG31: 6 | AH31: =+$AG$10 -> 8400 | AI31: =+$AG$13 -> 682.10548 | AJ31: 0 | AK31: =+AI31+AJ31 -> 682.10548
A32: 13 | B32: 4 | C32: =G31 -> 6720 | D32: =C32*$B$8 -> 351.07908 | E32: =IF(B32=1,0,IF(B32<10,$B$12*0.1/4,$B$12*0.2/4)) -> 210 | F32: =D32+E32 -> 561.07908 | G32: =C32-E32 -> 6510 | I32: ESQUEMA DE AMORTIZACIÓN DE CAPITAL | P32: 11 | Q32: =CEILING(P32/4,1) -> 3 | R32: =V31 -> 8170.6211 | S32: =R32*$Q$9 -> 407.16928 | T32: =IF(Q32<=$Q$16,0,$Q$17-S32) -> 123.33197 | U32: =S32+T32 -> 530.50126 | V32: =R32-T32 -> 8047.2891 | X32: TOTAL | Y32: =SUM(Y22:Y31) -> 9698.5595 | Z32: =SUM(Z22:Z31) -> 8400 | AA32: =SUM(AA22:AA31) -> 18098.559 | AF32: 13 | AG32: 7 | AH32: =+$AG$10 -> 8400 | AI32: =+$AG$13 -> 682.10548 | AJ32: 0 | AK32: =+AI32+AJ32 -> 682.10548
A33: 14 | B33: 4 | C33: =G32 -> 6510 | D33: =C33*$B$8 -> 340.10786 | E33: =IF(B33=1,0,IF(B33<10,$B$12*0.1/4,$B$12*0.2/4)) -> 210 | F33: =D33+E33 -> 550.10786 | G33: =C33-E33 -> 6300 | I33: Año | J33: % Capital | K33: Monto Amort. | L33: Descripción | P33: 12 | Q33: =CEILING(P33/4,1) -> 3 | R33: =V32 -> 8047.2891 | S33: =R33*$Q$9 -> 401.02324 | T33: =IF(Q33<=$Q$16,0,$Q$17-S33) -> 129.47802 | U33: =S33+T33 -> 530.50126 | V33: =R33-T33 -> 7917.8111 | AF33: 14 | AG33: 7 | AH33: =+$AG$10 -> 8400 | AI33: =+$AG$13 -> 682.10548 | AJ33: 0 | AK33: =+AI33+AJ33 -> 682.10548
A34: 15 | B34: 4 | C34: =G33 -> 6300 | D34: =C34*$B$8 -> 329.13663 | E34: =IF(B34=1,0,IF(B34<10,$B$12*0.1/4,$B$12*0.2/4)) -> 210 | F34: =D34+E34 -> 539.13663 | G34: =C34-E34 -> 6090 | I34: 1 | J34: 0 | K34: =B12*0 -> 0 | L34: Período de gracia | P34: 13 | Q34: =CEILING(P34/4,1) -> 4 | R34: =V33 -> 7917.8111 | S34: =R34*$Q$9 -> 394.57092 | T34: =IF(Q34<=$Q$16,0,$Q$17-S34) -> 135.93034 | U34: =S34+T34 -> 530.50126 | V34: =R34-T34 -> 7781.8807 | AF34: 15 | AG34: 8 | AH34: =+$AG$10 -> 8400 | AI34: =+$AG$13 -> 682.10548 | AJ34: 0 | AK34: =+AI34+AJ34 -> 682.10548
A35: 16 | B35: 4 | C35: =G34 -> 6090 | D35: =C35*$B$8 -> 318.16541 | E35: =IF(B35=1,0,IF(B35<10,$B$12*0.1/4,$B$12*0.2/4)) -> 210 | F35: =D35+E35 -> 528.16541 | G35: =C35-E35 -> 5880 | I35: 2 | J35: 0.1 | K35: =B12*0.1 -> 840 | L35: Amortización regular | P35: 14 | Q35: =CEILING(P35/4,1) -> 4 | R35: =V34 -> 7781.8807 | S35: =R35*$Q$9 -> 387.79706 | T35: =IF(Q35<=$Q$16,0,$Q$17-S35) -> 142.7042 | U35: =S35+T35 -> 530.50126 | V35: =R35-T35 -> 7639.1766 | AF35: 16 | AG35: 8 | AH35: =+$AG$10 -> 8400 | AI35: =+$AG$13 -> 682.10548 | AJ35: 0 | AK35: =+AI35+AJ35 -> 682.10548
A36: 17 | B36: 5 | C36: =G35 -> 5880 | D36: =C36*$B$8 -> 307.19419 | E36: =IF(B36=1,0,IF(B36<10,$B$12*0.1/4,$B$12*0.2/4)) -> 210 | F36: =D36+E36 -> 517.19419 | G36: =C36-E36 -> 5670 | I36: 3 | J36: 0.1 | K36: =B12*0.1 -> 840 | L36: Amortización regular | P36: 15 | Q36: =CEILING(P36/4,1) -> 4 | R36: =V35 -> 7639.1766 | S36: =R36*$Q$9 -> 380.68563 | T36: =IF(Q36<=$Q$16,0,$Q$17-S36) -> 149.81562 | U36: =S36+T36 -> 530.50126 | V36: =R36-T36 -> 7489.3609 | AF36: 17 | AG36: 9 | AH36: =+$AG$10 -> 8400 | AI36: =+$AG$13 -> 682.10548 | AJ36: 0 | AK36: =+AI36+AJ36 -> 682.10548
A37: 18 | B37: 5 | C37: =G36 -> 5670 | D37: =C37*$B$8 -> 296.22297 | E37: =IF(B37=1,0,IF(B37<10,$B$12*0.1/4,$B$12*0.2/4)) -> 210 | F37: =D37+E37 -> 506.22297 | G37: =C37-E37 -> 5460 | I37: 4 | J37: 0.1 | K37: =B12*0.1 -> 840 | L37: Amortización regular | P37: 16 | Q37: =CEILING(P37/4,1) -> 4 | R37: =V36 -> 7489.3609 | S37: =R37*$Q$9 -> 373.21982 | T37: =IF(Q37<=$Q$16,0,$Q$17-S37) -> 157.28144 | U37: =S37+T37 -> 530.50126 | V37: =R37-T37 -> 7332.0795 | AF37: 18 | AG37: 9 | AH37: =+$AG$10 -> 8400 | AI37: =+$AG$13 -> 682.10548 | AJ37: 0 | AK37: =+AI37+AJ37 -> 682.10548
A38: 19 | B38: 5 | C38: =G37 -> 5460 | D38: =C38*$B$8 -> 285.25175 | E38: =IF(B38=1,0,IF(B38<10,$B$12*0.1/4,$B$12*0.2/4)) -> 210 | F38: =D38+E38 -> 495.25175 | G38: =C38-E38 -> 5250 | I38: 5 | J38: 0.1 | K38: =B12*0.1 -> 840 | L38: Amortización regular | P38: 17 | Q38: =CEILING(P38/4,1) -> 5 | R38: =V37 -> 7332.0795 | S38: =R38*$Q$9 -> 365.38196 | T38: =IF(Q38<=$Q$16,0,$Q$17-S38) -> 165.11929 | U38: =S38+T38 -> 530.50126 | V38: =R38-T38 -> 7166.9602 | AF38: 19 | AG38: 10 | AH38: =+$AG$10 -> 8400 | AI38: =+$AG$13 -> 682.10548 | AJ38: 0 | AK38: =+AI38+AJ38 -> 682.10548
A39: 20 | B39: 5 | C39: =G38 -> 5250 | D39: =C39*$B$8 -> 274.28053 | E39: =IF(B39=1,0,IF(B39<10,$B$12*0.1/4,$B$12*0.2/4)) -> 210 | F39: =D39+E39 -> 484.28053 | G39: =C39-E39 -> 5040 | I39: 6 | J39: 0.1 | K39: =B12*0.1 -> 840 | L39: Amortización regular | P39: 18 | Q39: =CEILING(P39/4,1) -> 5 | R39: =V38 -> 7166.9602 | S39: =R39*$Q$9 -> 357.15352 | T39: =IF(Q39<=$Q$16,0,$Q$17-S39) -> 173.34774 | U39: =S39+T39 -> 530.50126 | V39: =R39-T39 -> 6993.6125 | AF39: 20 | AG39: 10 | AH39: =+$AG$10 -> 8400 | AI39: =+$AG$13 -> 682.10548 | AJ39: =+AG10 -> 8400 | AK39: =+AI39+AJ39 -> 9082.1055
A40: 21 | B40: 6 | C40: =G39 -> 5040 | D40: =C40*$B$8 -> 263.30931 | E40: =IF(B40=1,0,IF(B40<10,$B$12*0.1/4,$B$12*0.2/4)) -> 210 | F40: =D40+E40 -> 473.30931 | G40: =C40-E40 -> 4830 | I40: 7 | J40: 0.1 | K40: =B12*0.1 -> 840 | L40: Amortización regular | P40: 19 | Q40: =CEILING(P40/4,1) -> 5 | R40: =V39 -> 6993.6125 | S40: =R40*$Q$9 -> 348.51502 | T40: =IF(Q40<=$Q$16,0,$Q$17-S40) -> 181.98624 | U40: =S40+T40 -> 530.50126 | V40: =R40-T40 -> 6811.6262 | AF40: TOTALES | AI40: =SUM(AI20:AI39) -> 13642.11 | AJ40: =SUM(AJ20:AJ39) -> 8400 | AK40: =SUM(AK20:AK39) -> 22042.11
A41: 22 | B41: 6 | C41: =G40 -> 4830 | D41: =C41*$B$8 -> 252.33809 | E41: =IF(B41=1,0,IF(B41<10,$B$12*0.1/4,$B$12*0.2/4)) -> 210 | F41: =D41+E41 -> 462.33809 | G41: =C41-E41 -> 4620 | I41: 8 | J41: 0.1 | K41: =B12*0.1 -> 840 | L41: Amortización regular | P41: 20 | Q41: =CEILING(P41/4,1) -> 5 | R41: =V40 -> 6811.6262 | S41: =R41*$Q$9 -> 339.44604 | T41: =IF(Q41<=$Q$16,0,$Q$17-S41) -> 191.05522 | U41: =S41+T41 -> 530.50126 | V41: =R41-T41 -> 6620.571
A42: 23 | B42: 6 | C42: =G41 -> 4620 | D42: =C42*$B$8 -> 241.36686 | E42: =IF(B42=1,0,IF(B42<10,$B$12*0.1/4,$B$12*0.2/4)) -> 210 | F42: =D42+E42 -> 451.36686 | G42: =C42-E42 -> 4410 | I42: 9 | J42: 0.1 | K42: =B12*0.1 -> 840 | L42: Amortización regular | P42: 21 | Q42: =CEILING(P42/4,1) -> 6 | R42: =V41 -> 6620.571 | S42: =R42*$Q$9 -> 329.92512 | T42: =IF(Q42<=$Q$16,0,$Q$17-S42) -> 200.57613 | U42: =S42+T42 -> 530.50126 | V42: =R42-T42 -> 6419.9949 | AF42: Capital (Valor Nominal) | AG42: =+AG10 -> 8400
A43: 24 | B43: 6 | C43: =G42 -> 4410 | D43: =C43*$B$8 -> 230.39564 | E43: =IF(B43=1,0,IF(B43<10,$B$12*0.1/4,$B$12*0.2/4)) -> 210 | F43: =D43+E43 -> 440.39564 | G43: =C43-E43 -> 4200 | I43: 10 | J43: 0.2 | K43: =B12*0.2 -> 1680 | L43: Pago al vencimiento | P43: 22 | Q43: =CEILING(P43/4,1) -> 6 | R43: =V42 -> 6419.9949 | S43: =R43*$Q$9 -> 319.92974 | T43: =IF(Q43<=$Q$16,0,$Q$17-S43) -> 210.57151 | U43: =S43+T43 -> 530.50126 | V43: =R43-T43 -> 6209.4234 | AF43: Total Intereses (Cupones) | AG43: =+AI40 -> 13642.11
A44: 25 | B44: 7 | C44: =G43 -> 4200 | D44: =C44*$B$8 -> 219.42442 | E44: =IF(B44=1,0,IF(B44<10,$B$12*0.1/4,$B$12*0.2/4)) -> 210 | F44: =D44+E44 -> 429.42442 | G44: =C44-E44 -> 3990 | I44: Total | J44: 1 | K44: =SUM(K34:K43) -> 8400 | P44: 23 | Q44: =CEILING(P44/4,1) -> 6 | R44: =V43 -> 6209.4234 | S44: =R44*$Q$9 -> 309.43626 | T44: =IF(Q44<=$Q$16,0,$Q$17-S44) -> 221.06499 | U44: =S44+T44 -> 530.50126 | V44: =R44-T44 -> 5988.3584 | AF44: Gastos de Emisión | AG44: =+AG12 -> 2100
A45: 26 | B45: 7 | C45: =G44 -> 3990 | D45: =C45*$B$8 -> 208.4532 | E45: =IF(B45=1,0,IF(B45<10,$B$12*0.1/4,$B$12*0.2/4)) -> 210 | F45: =D45+E45 -> 418.4532 | G45: =C45-E45 -> 3780 | P45: 24 | Q45: =CEILING(P45/4,1) -> 6 | R45: =V44 -> 5988.3584 | S45: =R45*$Q$9 -> 298.41986 | T45: =IF(Q45<=$Q$16,0,$Q$17-S45) -> 232.0814 | U45: =S45+T45 -> 530.50126 | V45: =R45-T45 -> 5756.277 | AF45: COSTO TOTAL DE LA EMISIÓN | AG45: =+AG43+AG44 -> 15742.11
A46: 27 | B46: 7 | C46: =G45 -> 3780 | D46: =C46*$B$8 -> 197.48198 | E46: =IF(B46=1,0,IF(B46<10,$B$12*0.1/4,$B$12*0.2/4)) -> 210 | F46: =D46+E46 -> 407.48198 | G46: =C46-E46 -> 3570 | P46: 25 | Q46: =CEILING(P46/4,1) -> 7 | R46: =V45 -> 5756.277 | S46: =R46*$Q$9 -> 286.85447 | T46: =IF(Q46<=$Q$16,0,$Q$17-S46) -> 243.64679 | U46: =S46+T46 -> 530.50126 | V46: =R46-T46 -> 5512.6302
A47: 28 | B47: 7 | C47: =G46 -> 3570 | D47: =C47*$B$8 -> 186.51076 | E47: =IF(B47=1,0,IF(B47<10,$B$12*0.1/4,$B$12*0.2/4)) -> 210 | F47: =D47+E47 -> 396.51076 | G47: =C47-E47 -> 3360 | P47: 26 | Q47: =CEILING(P47/4,1) -> 7 | R47: =V46 -> 5512.6302 | S47: =R47*$Q$9 -> 274.71274 | T47: =IF(Q47<=$Q$16,0,$Q$17-S47) -> 255.78852 | U47: =S47+T47 -> 530.50126 | V47: =R47-T47 -> 5256.8417
A48: 29 | B48: 8 | C48: =G47 -> 3360 | D48: =C48*$B$8 -> 175.53954 | E48: =IF(B48=1,0,IF(B48<10,$B$12*0.1/4,$B$12*0.2/4)) -> 210 | F48: =D48+E48 -> 385.53954 | G48: =C48-E48 -> 3150 | P48: 27 | Q48: =CEILING(P48/4,1) -> 7 | R48: =V47 -> 5256.8417 | S48: =R48*$Q$9 -> 261.96594 | T48: =IF(Q48<=$Q$16,0,$Q$17-S48) -> 268.53531 | U48: =S48+T48 -> 530.50126 | V48: =R48-T48 -> 4988.3063
A49: 30 | B49: 8 | C49: =G48 -> 3150 | D49: =C49*$B$8 -> 164.56832 | E49: =IF(B49=1,0,IF(B49<10,$B$12*0.1/4,$B$12*0.2/4)) -> 210 | F49: =D49+E49 -> 374.56832 | G49: =C49-E49 -> 2940 | P49: 28 | Q49: =CEILING(P49/4,1) -> 7 | R49: =V48 -> 4988.3063 | S49: =R49*$Q$9 -> 248.58393 | T49: =IF(Q49<=$Q$16,0,$Q$17-S49) -> 281.91732 | U49: =S49+T49 -> 530.50126 | V49: =R49-T49 -> 4706.389
A50: 31 | B50: 8 | C50: =G49 -> 2940 | D50: =C50*$B$8 -> 153.5971 | E50: =IF(B50=1,0,IF(B50<10,$B$12*0.1/4,$B$12*0.2/4)) -> 210 | F50: =D50+E50 -> 363.5971 | G50: =C50-E50 -> 2730 | P50: 29 | Q50: =CEILING(P50/4,1) -> 8 | R50: =V49 -> 4706.389 | S50: =R50*$Q$9 -> 234.53505 | T50: =IF(Q50<=$Q$16,0,$Q$17-S50) -> 295.9662 | U50: =S50+T50 -> 530.50126 | V50: =R50-T50 -> 4410.4228
A51: 32 | B51: 8 | C51: =G50 -> 2730 | D51: =C51*$B$8 -> 142.62587 | E51: =IF(B51=1,0,IF(B51<10,$B$12*0.1/4,$B$12*0.2/4)) -> 210 | F51: =D51+E51 -> 352.62587 | G51: =C51-E51 -> 2520 | P51: 30 | Q51: =CEILING(P51/4,1) -> 8 | R51: =V50 -> 4410.4228 | S51: =R51*$Q$9 -> 219.78607 | T51: =IF(Q51<=$Q$16,0,$Q$17-S51) -> 310.71519 | U51: =S51+T51 -> 530.50126 | V51: =R51-T51 -> 4099.7076
A52: 33 | B52: 9 | C52: =G51 -> 2520 | D52: =C52*$B$8 -> 131.65465 | E52: =IF(B52=1,0,IF(B52<10,$B$12*0.1/4,$B$12*0.2/4)) -> 210 | F52: =D52+E52 -> 341.65465 | G52: =C52-E52 -> 2310 | P52: 31 | Q52: =CEILING(P52/4,1) -> 8 | R52: =V51 -> 4099.7076 | S52: =R52*$Q$9 -> 204.3021 | T52: =IF(Q52<=$Q$16,0,$Q$17-S52) -> 326.19916 | U52: =S52+T52 -> 530.50126 | V52: =R52-T52 -> 3773.5085
A53: 34 | B53: 9 | C53: =G52 -> 2310 | D53: =C53*$B$8 -> 120.68343 | E53: =IF(B53=1,0,IF(B53<10,$B$12*0.1/4,$B$12*0.2/4)) -> 210 | F53: =D53+E53 -> 330.68343 | G53: =C53-E53 -> 2100 | P53: 32 | Q53: =CEILING(P53/4,1) -> 8 | R53: =V52 -> 3773.5085 | S53: =R53*$Q$9 -> 188.04651 | T53: =IF(Q53<=$Q$16,0,$Q$17-S53) -> 342.45475 | U53: =S53+T53 -> 530.50126 | V53: =R53-T53 -> 3431.0537
A54: 35 | B54: 9 | C54: =G53 -> 2100 | D54: =C54*$B$8 -> 109.71221 | E54: =IF(B54=1,0,IF(B54<10,$B$12*0.1/4,$B$12*0.2/4)) -> 210 | F54: =D54+E54 -> 319.71221 | G54: =C54-E54 -> 1890 | P54: 33 | Q54: =CEILING(P54/4,1) -> 9 | R54: =V53 -> 3431.0537 | S54: =R54*$Q$9 -> 170.98084 | T54: =IF(Q54<=$Q$16,0,$Q$17-S54) -> 359.52041 | U54: =S54+T54 -> 530.50126 | V54: =R54-T54 -> 3071.5333
A55: 36 | B55: 9 | C55: =G54 -> 1890 | D55: =C55*$B$8 -> 98.74099 | E55: =IF(B55=1,0,IF(B55<10,$B$12*0.1/4,$B$12*0.2/4)) -> 210 | F55: =D55+E55 -> 308.74099 | G55: =C55-E55 -> 1680 | P55: 34 | Q55: =CEILING(P55/4,1) -> 9 | R55: =V54 -> 3071.5333 | S55: =R55*$Q$9 -> 153.06474 | T55: =IF(Q55<=$Q$16,0,$Q$17-S55) -> 377.43651 | U55: =S55+T55 -> 530.50126 | V55: =R55-T55 -> 2694.0968
A56: 37 | B56: 10 | C56: =G55 -> 1680 | D56: =C56*$B$8 -> 87.769769 | E56: =IF(B56=1,0,IF(B56<10,$B$12*0.1/4,$B$12*0.2/4)) -> 420 | F56: =D56+E56 -> 507.76977 | G56: =C56-E56 -> 1260 | P56: 35 | Q56: =CEILING(P56/4,1) -> 9 | R56: =V55 -> 2694.0968 | S56: =R56*$Q$9 -> 134.25582 | T56: =IF(Q56<=$Q$16,0,$Q$17-S56) -> 396.24543 | U56: =S56+T56 -> 530.50126 | V56: =R56-T56 -> 2297.8514
A57: 38 | B57: 10 | C57: =G56 -> 1260 | D57: =C57*$B$8 -> 65.827327 | E57: =IF(B57=1,0,IF(B57<10,$B$12*0.1/4,$B$12*0.2/4)) -> 420 | F57: =D57+E57 -> 485.82733 | G57: =C57-E57 -> 840 | P57: 36 | Q57: =CEILING(P57/4,1) -> 9 | R57: =V56 -> 2297.8514 | S57: =R57*$Q$9 -> 114.50959 | T57: =IF(Q57<=$Q$16,0,$Q$17-S57) -> 415.99166 | U57: =S57+T57 -> 530.50126 | V57: =R57-T57 -> 1881.8597
... A59: 40 | B59: 10 | C59: =G58 -> 420 | D59: =C59*$B$8 -> 21.942442 | E59: =IF(B59=1,0,IF(B59<10,$B$12*0.1/4,$B$12*0.2/4)) -> 420 | F59: =D59+E59 -> 441.94244 | G59: =C59-E59 -> 0 | P59: 38 | Q59: =CEILING(P59/4,1) -> 10 | R59: =V58 -> 1445.1378 | S59: =R59*$Q$9 -> 72.016033 | T59: =IF(Q59<=$Q$16,0,$Q$17-S59) -> 458.48522 | U59: =S59+T59 -> 530.50126 | V59: =R59-T59 -> 986.65257
A60: TOTALES | D60: =SUM(D20:D59) -> 10576.257 | E60: =SUM(E20:E59) -> 8400 | F60: =SUM(F20:F59) -> 18976.257 | P60: 39 | Q60: =CEILING(P60/4,1) -> 10 | R60: =V59 -> 986.65257 | S60: =R60*$Q$9 -> 49.168186 | T60: =IF(Q60<=$Q$16,0,$Q$17-S60) -> 481.33307 | U60: =S60+T60 -> 530.50126 | V60: =R60-T60 -> 505.3195
P61: 40 | Q61: =CEILING(P61/4,1) -> 10 | R61: =V60 -> 505.3195 | S61: =R61*$Q$9 -> 25.181755 | T61: =IF(Q61<=$Q$16,0,$Q$17-S61) -> 505.3195 | U61: =S61+T61 -> 530.50126 | V61: =MAX(0,R61-T61) -> 0
A62: RESUMEN DEL CRÉDITO | P62: TOTALES | S62: =SUM(S22:S61) -> 11924.84 | T62: =SUM(T22:T61) -> 8400 | U62: =SUM(U22:U61) -> 20324.84
A63: Total Intereses Pagados | B63: =D60 -> 10576.257
A64: Total Capital Amortizado | B64: =E60 -> 8400 | P64: RESUMEN DEL CRÉDITO
A65: Total Pagado (Capital + Intereses) | B65: =F60 -> 18976.257 | P65: Total Intereses Pagados | Q65: =S62 -> 11924.84
A66: Costo Total del Crédito (Intereses + Gastos) | B66: =D60+B14 -> 11080.257 | P66: Total Capital Amortizado | Q66: =T62 -> 8400
P67: Total Pagado (Capital + Intereses) | Q67: =U62 -> 20324.84
P68: Costo Total del Crédito (Intereses + Gastos) | Q68: =S62+Q14 -> 12386.84

Sheet WACC
A1: Tasa libre de riesgo (Rf) | B1: 0.0444 | C1: https://www.bloomberg.com/markets/rates-bonds/government-bonds/us
A2: Retorno esperado del mercado | B2: 0.12591818
A3: Equity Risk Premium | B3: =B2-B1 -> 0.081518182
A4: Beta de la empresa apalancado (βL) | B4: 1.04 | C4: Metales y minería
A5: D/E sector | B5: 0.1098
A6: Tasa impositiva Colombia | B6: =Datos!C17 -> 0.35
A7: Beta de la empresa desapalancado (βU) | B7: =((B4)/(1+(1-B6)*B5)) -> 0.97071973 | C7: Calculado
A8: Beta del sector desapalancado (βU) | B8: 0.96 | C8: Damodaran, Metales y minería
A9: D/E ratio | B9: =Datos!C35/Datos!C34 -> 1.5 | C9: (10%D / 90%E)
A10: Beta reapalancado a la estructura del proyecto (βLproyecto) | B10: =B7*(1+(1-B6)*(B9)) -> 1.9171715 | C10: Calculado
A11: Bono Yankee_TES Globales de Colombia en USD a 10 años | B11: 0.06643 | C11: https://www.grupoaval.com/wps/portal/grupo-aval/aval/portal-financiero/renta-fija/yankees
A12: Riesgo país (Rp) | B12: =B11-B1 -> 0.02203 | C12: Calculado
A13: TES de Colombia en COP a 10 años | B13: 0.121 | C13: https://www.grupoaval.com/wps/portal/grupo-aval/aval/portal-financiero/renta-fija/tes/curva-rentabilidad
A14: Devaluación esperada | B14: =B13-B11 -> 0.05457 | C14: Calculado
A15: Ke_USD | B15: =B1+B10*B3+B12 -> 0.22271433
A16: Ke_COP | B16: =(1+B15)*(1+B14)-1 -> 0.28943785
A18: WACC | B18: =$B$16*Datos!$C$34+Datos!$C$35*Bancos!$B$10*(1-B6) -> 0.20388785

Sheet Depreciaciones
A1: Detalle | B1: Año 1 | C1: Año 2 | D1: Año 3 | E1: Año 4 | F1: Año 5 | G1: Año 6 | H1: Año 7 | I1: Año 8 | J1: Año 9 | K1: Año 10 | M1: Posible renovación total | N1: Página 5, nota 13
A2: Maquinaria y Equipos | B2: =Datos!$C$5*1000000/Datos!$E$5 -> 425000000 | C2: =Datos!$C$5*1000000/Datos!$E$5 -> 425000000 | D2: =Datos!$C$5*1000000/Datos!$E$5 -> 425000000 | E2: =Datos!$C$5*1000000/Datos!$E$5 -> 425000000 | F2: =Datos!$C$5*1000000/Datos!$E$5 -> 425000000 | G2: =Datos!$C$5*1000000/Datos!$E$5 -> 425000000 | H2: =Datos!$C$5*1000000/Datos!$E$5 -> 425000000 | I2: =Datos!$C$5*1000000/Datos!$E$5 -> 425000000 | ... K2: =Datos!$C$5*1000000/Datos!$E$5 -> 425000000 | M2: Sobre el activo fijo "maquina"
A3: Muebles y Enseres | B3: =Datos!$C$6*1000000/Datos!$E$6 -> 250000000 | C3: =Datos!$C$6*1000000/Datos!$E$6 -> 250000000 | D3: =Datos!$C$6*1000000/Datos!$E$6 -> 250000000 | E3: =Datos!$C$6*1000000/Datos!$E$6 -> 250000000 | F3: =Datos!$C$6*1000000/Datos!$E$6 -> 250000000 | G3: =Datos!$C$6*1000000/Datos!$E$6 -> 250000000 | H3: =Datos!$C$6*1000000/Datos!$E$6 -> 250000000 | I3: =Datos!$C$6*1000000/Datos!$E$6 -> 250000000 | ... K3: =Datos!$C$6*1000000/Datos!$E$6 -> 250000000 | M3: Genera nueva depreciacion desde el año 5
A4: Obras Civiles | B4: =Datos!$C$7*1000000/Datos!$E$7 -> 19800000 | C4: =Datos!$C$7*1000000/Datos!$E$7 -> 19800000 | D4: =Datos!$C$7*1000000/Datos!$E$7 -> 19800000 | E4: =Datos!$C$7*1000000/Datos!$E$7 -> 19800000 | F4: =Datos!$C$7*1000000/Datos!$E$7 -> 19800000 | G4: =Datos!$C$7*1000000/Datos!$E$7 -> 19800000 | H4: =Datos!$C$7*1000000/Datos!$E$7 -> 19800000 | I4: =Datos!$C$7*1000000/Datos!$E$7 -> 19800000 | ... K4: =Datos!$C$7*1000000/Datos!$E$7 -> 19800000
A5: Montaje | B5: =Datos!$C$8*1000000/Datos!$E$8 -> 42500000 | C5: =Datos!$C$8*1000000/Datos!$E$8 -> 42500000 | D5: =Datos!$C$8*1000000/Datos!$E$8 -> 42500000 | E5: =Datos!$C$8*1000000/Datos!$E$8 -> 42500000 | F5: =Datos!$C$8*1000000/Datos!$E$8 -> 42500000 | G5: =Datos!$C$8*1000000/Datos!$E$8 -> 42500000 | H5: =Datos!$C$8*1000000/Datos!$E$8 -> 42500000 | I5: =Datos!$C$8*1000000/Datos!$E$8 -> 42500000 | ... K5: =Datos!$C$8*1000000/Datos!$E$8 -> 42500000
A6: Transporte de Equipos | B6: =Datos!$C$9*1000000/Datos!$E$9 -> 62500000 | C6: =Datos!$C$9*1000000/Datos!$E$9 -> 62500000 | D6: =Datos!$C$9*1000000/Datos!$E$9 -> 62500000 | E6: =Datos!$C$9*1000000/Datos!$E$9 -> 62500000 | F6: =Datos!$C$9*1000000/Datos!$E$9 -> 62500000 | G6: =Datos!$C$9*1000000/Datos!$E$9 -> 62500000 | H6: =Datos!$C$9*1000000/Datos!$E$9 -> 62500000 | I6: =Datos!$C$9*1000000/Datos!$E$9 -> 62500000 | ... K6: =Datos!$C$9*1000000/Datos!$E$9 -> 62500000
A7: Total | B7: =SUM(B2:B6) -> 799800000 | C7: =SUM(C2:C6) -> 799800000 | D7: =SUM(D2:D6) -> 799800000 | E7: =SUM(E2:E6) -> 799800000 | F7: =SUM(F2:F6) -> 799800000 | G7: =SUM(G2:G6) -> 799800000 | H7: =SUM(H2:H6) -> 799800000 | I7: =SUM(I2:I6) -> 799800000 | ... K7: =SUM(K2:K6) -> 799800000

Sheet Amortización gasto seguro
A1: Detalle | B1: Año 1 | C1: Año 2 | D1: Año 3 | E1: Año 4 | F1: Año 5 | G1: Año 6 | H1: Año 7 | I1: Año 8 | J1: Año 9 | K1: Año 10
A2: Seguro en primeros 5 años | B2: =1000000*Datos!$C$10*Datos!$C$25/5 -> 280000000 | C2: =1000000*Datos!$C$10*Datos!$C$25/5 -> 280000000 | D2: =1000000*Datos!$C$10*Datos!$C$25/5 -> 280000000 | E2: =1000000*Datos!$C$10*Datos!$C$25/5 -> 280000000 | F2: =1000000*Datos!$C$10*Datos!$C$25/5 -> 280000000 | G2: 0 | H2: 0 | I2: 0 | J2: 0 | K2: 0
A3: Seguro en segundos 5 años | B3: 0 | C3: 0 | D3: 0 | E3: 0 | F3: 0 | G3: =1000000*Datos!$C$10*Datos!$C$25/5 -> 280000000 | H3: =1000000*Datos!$C$10*Datos!$C$25/5 -> 280000000 | I3: =1000000*Datos!$C$10*Datos!$C$25/5 -> 280000000 | J3: =1000000*Datos!$C$10*Datos!$C$25/5 -> 280000000 | K3: =1000000*Datos!$C$10*Datos!$C$25/5 -> 280000000
A4: Total | B4: =SUM(B2:B3) -> 280000000 | C4: =SUM(C2:C3) -> 280000000 | D4: =SUM(D2:D3) -> 280000000 | E4: =SUM(E2:E3) -> 280000000 | F4: =SUM(F2:F3) -> 280000000 | G4: =SUM(G2:G3) -> 280000000 | H4: =SUM(H2:H3) -> 280000000 | I4: =SUM(I2:I3) -> 280000000 | ... K4: =SUM(K2:K3) -> 280000000

Sheet Estado de resultados
B1: Año | C1: Año 0 | D1: Año 1 | E1: Año 2 | F1: Año 3 | G1: Año 4 | H1: Año 5 | I1: Año 6 | J1: Año 7 | K1: Año 8 | L1: Año 9 | M1: Año 10
B2: Consecutivo | C2: 0 | D2: 1 | E2: 2 | F2: 3 | G2: 4 | H2: 5 | I2: 6 | J2: 7 | K2: 8 | L2: 9 | M2: 10
B4: Inflación | D4: 0.0584 | E4: 0.0684 | F4: 0.0658 | G4: 0.0637 | H4: 0.06175 | I4: 0.0585 | J4: 0.05815 | K4: 0.0588 | L4: 0.0586 | M4: 0.0585
B5: Tasa de impuestos | D5: 0.35 | E5: 0.35 | F5: 0.35 | G5: 0.35 | H5: 0.35 | I5: 0.35 | J5: 0.35 | K5: 0.35 | L5: 0.35 | M5: 0.35
B8: Precio | D8: =6500000 -> 6500000 | E8: =D8*(1+D4)*(1+Datos!$C$31) -> 7292376 | F8: =E8*(1+E4)*(1+Datos!$C$31) -> 8258645 | G8: =F8*(1+F4)*(1+Datos!$C$31) -> 9330187.7 | H8: =G8*(1+G4)*(1+Datos!$C$31) -> 10519992 | I8: =H8*(1+H4)*(1+Datos!$C$31) -> 11839777 | J8: =I8*(1+I4)*(1+Datos!$C$31) -> 13284349 | K8: =J8*(1+J4)*(1+Datos!$C$31) -> 14900244 | L8: =K8*(1+K4)*(1+Datos!$C$31) -> 16722961 | M8: =L8*(1+L4)*(1+Datos!$C$31) -> 18765102
B9: Costo | D9: =Datos!C22 -> 1600000 | E9: =D9*(1+D4)*(1+Datos!$C$23) -> 1727308.8 | F9: =E9*(1+E4)*(1+Datos!$C$23) -> 1882365.9 | G9: =F9*(1+F4)*(1+Datos!$C$23) -> 2046350 | H9: =G9*(1+G4)*(1+Datos!$C$23) -> 2220236.6 | I9: =H9*(1+H4)*(1+Datos!$C$23) -> 2404482.9 | J9: =I9*(1+I4)*(1+Datos!$C$23) -> 2596048.1 | K9: =J9*(1+J4)*(1+Datos!$C$23) -> 2801948.4 | L9: =K9*(1+K4)*(1+Datos!$C$23) -> 3026037.1 | M9: =L9*(1+L4)*(1+Datos!$C$23) -> 3267430.1
B10: Cantidades | D10: 1500 | E10: 5000 | F10: 5000 | G10: 5000 | H10: 5000 | I10: 5000 | J10: 5000 | K10: 5000 | L10: 5000 | M10: 5000
B14: ESTADO DE RESULTADOS | C14: Año 0 | D14: Año 1 | E14: Año 2 | F14: Año 3 | G14: Año 4 | H14: Año 5 | I14: Año 6 | J14: Año 7 | K14: Año 8 | L14: Año 9 | M14: Año 10 | N14: Año 11
A15: =D15/$D$15 -> 1 | B15: Ingresos operacionales | D15: =D8*D10 -> 9750000000 | E15: =E8*E10 -> 36461880000 | F15: =F8*F10 -> 4.1293225e+10 | G15: =G8*G10 -> 4.6650938e+10 | H15: =H8*H10 -> 5.2599959e+10 | I15: =I8*I10 -> 5.9198887e+10 | J15: =J8*J10 -> 6.6421743e+10 | K15: =K8*K10 -> 7.4501218e+10 | ... M15: =M8*M10 -> 9.3825508e+10
A16: =D16/$D$15 -> 0.24615385 | B16: Costo de ventas | D16: =D9*D10 -> 2400000000 | E16: =E9*E10 -> 8636544000 | F16: =F9*F10 -> 9.4118293e+09 | G16: =G9*G10 -> 1.023175e+10 | H16: =H9*H10 -> 1.1101183e+10 | I16: =I9*I10 -> 1.2022415e+10 | J16: =J9*J10 -> 1.298024e+10 | K16: =K9*K10 -> 1.4009742e+10 | ... M16: =M9*M10 -> 1.633715e+10
A17: =D17/D15 -> 0.030769231 | B17: Costo de nómina asociada a la operación | D17: =Nómina!H3 -> 300000000 | E17: =D17*(1+D4) -> 317520000 | F17: =E17*(1+E4) -> 339238368 | G17: =F17*(1+F4) -> 3.6156025e+08 | H17: =G17*(1+G4) -> 3.8459164e+08 | I17: =H17*(1+H4) -> 4.0834017e+08 | J17: =I17*(1+I4) -> 4.3222807e+08 | K17: =J17*(1+J4) -> 4.5736214e+08 | L17: =K17*(1+K4) -> 4.8425503e+08 | M17: =L17*(1+L4) -> 5.1263238e+08
A18: =D18/D15 -> 0.055 | B18: Costo de mantenimiento | D18: =D15*Datos!$C$21 -> 536250000 | E18: =E15*Datos!$C$21 -> 2005403400 | F18: =F15*Datos!$C$21 -> 2.2711274e+09 | G18: =G15*Datos!$C$21 -> 2.5658016e+09 | H18: =H15*Datos!$C$21 -> 2.8929978e+09 | I18: =I15*Datos!$C$21 -> 3.2559388e+09 | J18: =J15*Datos!$C$21 -> 3.6531959e+09 | K18: =K15*Datos!$C$21 -> 4.097567e+09 | ... M18: =M15*Datos!$C$21 -> 5.1604029e+09
A19: =D19/$D$15 -> 0.66807692 | B19: Utilidad bruta | D19: =D15-D16-D17-D18 -> 6513750000 | E19: =E15-E16-E17-E18 -> 25502412600 | F19: =F15-F16-F17-F18 -> 2.927103e+10 | G19: =G15-G16-G17-G18 -> 3.3491826e+10 | H19: =H15-H16-H17-H18 -> 3.8221187e+10 | I19: =I15-I16-I17-I18 -> 4.3512194e+10 | J19: =J15-J16-J17-J18 -> 4.9356079e+10 | K19: =K15-K16-K17-K18 -> 5.5936546e+10 | ... M19: =M15-M16-M17-M18 -> 7.1815322e+10
A20: =D20/$D$15 -> 0.15261538 | B20: Costos de nómina administrativos | D20: =Nómina!H4 -> 1488000000 | E20: =D20*(1+D4) -> 1574899200 | F20: =E20*(1+E4) -> 1.6826223e+09 | G20: =F20*(1+F4) -> 1.7933389e+09 | H20: =G20*(1+G4) -> 1.9075745e+09 | I20: =H20*(1+H4) -> 2.0253673e+09 | J20: =I20*(1+I4) -> 2.1438513e+09 | K20: =J20*(1+J4) -> 2.2685162e+09 | L20: =K20*(1+K4) -> 2.401905e+09 | M20: =L20*(1+L4) -> 2.5426566e+09
A21: =D21/$D$15 -> 0.25 | B21: Gastos operacionales (variable) | D21: =D15*Datos!$C$26 -> 2437500000 | E21: =E15*Datos!$C$26 -> 9115470000 | F21: =F15*Datos!$C$26 -> 1.0323306e+10 | G21: =G15*Datos!$C$26 -> 1.1662735e+10 | H21: =H15*Datos!$C$26 -> 1.314999e+10 | I21: =I15*Datos!$C$26 -> 1.4799722e+10 | J21: =J15*Datos!$C$26 -> 1.6605436e+10 | K21: =K15*Datos!$C$26 -> 1.8625304e+10 | ... M21: =M15*Datos!$C$26 -> 2.3456377e+10
A22: =D22/$D$15 -> 0.082030769 | B22: Depreciación | D22: {=Depreciaciones!B7:K7} -> 799800000 | E22: 799800000 | F22: 799800000 | G22: 799800000 | H22: 799800000 | I22: 799800000 | J22: 799800000 | K22: 799800000 | L22: 799800000 | M22: 799800000
A23: =D23/$D$15 -> 0 | B23: Amortización | D23: =0 -> 0 | E23: =0 -> 0 | F23: =0 -> 0 | G23: =0 -> 0 | H23: =0 -> 0 | I23: =0 -> 0 | J23: =0 -> 0 | K23: =0 -> 0 | ... M23: =0 -> 0
A24: =D24/$D$15 -> 0.02 | B24: Comisiones | D24: =D15*Datos!$C$27 -> 195000000 | E24: =E15*Datos!$C$27 -> 729237600 | F24: =F15*Datos!$C$27 -> 8.258645e+08 | G24: =G15*Datos!$C$27 -> 9.3301877e+08 | H24: =H15*Datos!$C$27 -> 1.0519992e+09 | I24: =I15*Datos!$C$27 -> 1.1839777e+09 | J24: =J15*Datos!$C$27 -> 1.3284349e+09 | K24: =K15*Datos!$C$27 -> 1.4900244e+09 | ... M24: =M15*Datos!$C$27 -> 1.8765102e+09
A25: =D25/$D$15 -> 0.028717949 | B25: Gastos por seguro | D25: {='Amortización gasto seguro'!B4:K4} -> 280000000 | E25: 280000000 | F25: 280000000 | G25: 280000000 | H25: 280000000 | I25: 280000000 | J25: 280000000 | K25: 280000000 | L25: 280000000 | M25: 280000000
A26: =D26/$D$15 -> 0.13471282 | B26: EBIT | D26: =D19-D20-D21-D22-D23-D24-D25 -> 1313450000 | E26: =E19-E20-E21-E22-E23-E24 -> 13283005800 | F26: =F19-F20-F21-F22-F23-F24 -> 1.5639437e+10 | G26: =G19-G20-G21-G22-G23-G24 -> 1.8302934e+10 | H26: =H19-H20-H21-H22-H23-H24 -> 2.1311823e+10 | I26: =I19-I20-I21-I22-I23-I24 -> 2.4703327e+10 | J26: =J19-J20-J21-J22-J23-J24 -> 2.8478557e+10 | K26: =K19-K20-K21-K22-K23-K24 -> 3.2752901e+10 | L26: =L19-L20-L21-L22-L23-L24 -> 3.7623847e+10 | M26: =M19-M20-M21-M22-M23-M24 -> 4.3139978e+10
A27: =D27/$D$15 -> 0.0090020276 | B27: Gastos financieros (intereses) | D27: {=TRANSPOSE(Bancos!Y22:Y31)*100000} -> 87769769 | E27: 1.6895681e+08 | F27: 1.5140285e+08 | G27: 1.338489e+08 | H27: 1.1629494e+08 | I27: 98740990 | J27: 81187036 | K27: 63633083 | L27: 46079129 | M27: 21942442
A28: =D28/$D$15 -> 0.12571079 | B28: EBT | D28: =D26-D27 -> 1.2256802e+09 | E28: =E26-E27 -> 1.3114049e+10 | F28: =F26-F27 -> 1.5488034e+10 | G28: =G26-G27 -> 1.8169085e+10 | H28: =H26-H27 -> 2.1195528e+10 | I28: =I26-I27 -> 2.4604586e+10 | J28: =J26-J27 -> 2.839737e+10 | K28: =K26-K27 -> 3.2689268e+10 | ... M28: =M26-M27 -> 4.3118036e+10
A29: =D29/$D$15 -> 0.043998778 | B29: Provisión de impuestos | D29: =IF(D28<0,0,D28*D5) -> 4.2898808e+08 | E29: =IF(E28<0,0,E28*E5) -> 4.5899171e+09 | F29: =IF(F28<0,0,F28*F5) -> 5.4208119e+09 | G29: =IF(G28<0,0,G28*G5) -> 6.3591798e+09 | H29: =IF(H28<0,0,H28*H5) -> 7.418435e+09 | I29: =IF(I28<0,0,I28*I5) -> 8.611605e+09 | J29: =IF(J28<0,0,J28*J5) -> 9.9390795e+09 | K29: =IF(K28<0,0,K28*K5) -> 1.1441244e+10 | ... M29: =IF(M28<0,0,M28*M5) -> 1.5091313e+10
A30: =D30/$D$15 -> 0.081712015 | B30: Utilidad neta | D30: =D28-D29 -> 7.9669215e+08 | E30: =E28-E29 -> 8.5241318e+09 | F30: =F28-F29 -> 1.0067222e+10 | G30: =G28-G29 -> 1.1809905e+10 | H30: =H28-H29 -> 1.3777093e+10 | I30: =I28-I29 -> 1.5992981e+10 | J30: =J28-J29 -> 1.8458291e+10 | K30: =K28-K29 -> 2.1248024e+10 | ... M30: =M28-M29 -> 2.8026723e+10
B32: EBITDA | D32: =D26+D22+D23 -> 2113250000 | E32: =E26+E22+E23 -> 14082805800 | F32: =F26+F22+F23 -> 1.6439237e+10 | G32: =G26+G22+G23 -> 1.9102734e+10 | H32: =H26+H22+H23 -> 2.2111623e+10 | I32: =I26+I22+I23 -> 2.5503127e+10 | J32: =J26+J22+J23 -> 2.9278357e+10 | K32: =K26+K22+K23 -> 3.3552701e+10 | ... M32: =M26+M22+M23 -> 4.3939778e+10
A34: =D34/$D$15 -> 0.083333333 | B34: CXC | D34: =(Datos!$C$28/360)*'Estado de resultados'!D15 -> 812500000 | E34: =(Datos!$C$28/360)*'Estado de resultados'!E15 -> 3038490000 | F34: =(Datos!$C$28/360)*'Estado de resultados'!F15 -> 3.4411021e+09 | G34: =(Datos!$C$28/360)*'Estado de resultados'!G15 -> 3.8875782e+09 | H34: =(Datos!$C$28/360)*'Estado de resultados'!H15 -> 4.3833299e+09 | I34: =(Datos!$C$28/360)*'Estado de resultados'!I15 -> 4.9332406e+09 | J34: =(Datos!$C$28/360)*'Estado de resultados'!J15 -> 5.5351453e+09 | K34: =(Datos!$C$28/360)*'Estado de resultados'!K15 -> 6.2084348e+09 | ... M34: =(Datos!$C$28/360)*'Estado de resultados'!M15 -> 7.8187923e+09
B35: KTO | D35: =D34 -> 812500000 | E35: =E34 -> 3038490000 | F35: =F34 -> 3.4411021e+09 | G35: =G34 -> 3.8875782e+09 | H35: =H34 -> 4.3833299e+09 | I35: =I34 -> 4.9332406e+09 | J35: =J34 -> 5.5351453e+09 | K35: =K34 -> 6.2084348e+09 | ... M35: =M34 -> 7.8187923e+09
A36: =D36/$D$15 -> 0.061538462 | B36: CXP | D36: =(Datos!$C$29/360)*'Estado de resultados'!D16 -> 600000000 | E36: =(Datos!$C$29/360)*'Estado de resultados'!E16 -> 2159136000 | F36: =(Datos!$C$29/360)*'Estado de resultados'!F16 -> 2.3529573e+09 | G36: =(Datos!$C$29/360)*'Estado de resultados'!G16 -> 2.5579376e+09 | H36: =(Datos!$C$29/360)*'Estado de resultados'!H16 -> 2.7752957e+09 | I36: =(Datos!$C$29/360)*'Estado de resultados'!I16 -> 3.0056037e+09 | J36: =(Datos!$C$29/360)*'Estado de resultados'!J16 -> 3.2450601e+09 | K36: =(Datos!$C$29/360)*'Estado de resultados'!K16 -> 3.5024355e+09 | ... M36: =(Datos!$C$29/360)*'Estado de resultados'!M16 -> 4.0842876e+09
A37: =D37/$D$15 -> 0.043998778 | B37: Impuestos por pagar | D37: =D29 -> 4.2898808e+08 | E37: =E29 -> 4.5899171e+09 | F37: =F29 -> 5.4208119e+09 | G37: =G29 -> 6.3591798e+09 | H37: =H29 -> 7.418435e+09 | I37: =I29 -> 8.611605e+09 | J37: =J29 -> 9.9390795e+09 | K37: =K29 -> 1.1441244e+10 | ... M37: =M29 -> 1.5091313e+10
B38: KTNO | D38: =D35-D36-D37 -> -2.1648808e+08 | E38: =E35-E36-E37 -> -3.7105631e+09 | F38: =F35-F36-F37 -> -4.3326672e+09 | G38: =G35-G36-G37 -> -5.0295392e+09 | H38: =H35-H36-H37 -> -5.8104007e+09 | I38: =I35-I36-I37 -> -6.6839681e+09 | J38: =J35-J36-J37 -> -7.6489943e+09 | K38: =K35-K36-K37 -> -8.7352447e+09 | ... M38: =M35-M36-M37 -> -1.1356808e+10 | O38: Proyección venta de activos | P38: 0.3
B39: Δ KTNO | D39: =D38 -> -2.1648808e+08 | E39: =E38-D38 -> -3.4940751e+09 | F39: =F38-E38 -> -6.22104e+08 | G39: =G38-F38 -> -6.9687201e+08 | H39: =H38-G38 -> -7.8086159e+08 | I39: =I38-H38 -> -8.7356733e+08 | J39: =J38-I38 -> -9.6502624e+08 | K39: =K38-J38 -> -1.0862503e+09 | L39: =L38-K38 -> -1.23162e+09 | M39: =M38-L38 -> -1.3899432e+09 | O39: Costo de desmantelamiento | P39: 0.105
O40: Tasa de impuesto por ganancia ocasional | P40: 0.15
B41: PPE (Propiedades, Planta y Equipo) Bruta | C41: =Datos!C10*1000000 -> 14000000000 | D41: =C41 -> 14000000000 | E41: =D41 -> 14000000000 | F41: =E41 -> 14000000000 | G41: =F41 -> 14000000000 | H41: =G41 -> 14000000000 | I41: =H41 -> 14000000000 | J41: =I41 -> 14000000000 | K41: =J41 -> 14000000000 | ... M41: =L41 -> 14000000000
B42: Depreciación acumulada | D42: =D22 -> 799800000 | E42: =E22 -> 799800000 | F42: =F22 -> 799800000 | G42: =G22 -> 799800000 | H42: =H22 -> 799800000 | I42: =I22 -> 799800000 | J42: =J22 -> 799800000 | K42: =K22 -> 799800000 | ... M42: =M22 -> 799800000 | O42: Valor en venta esperado | P42: =Datos!$C$10*1000000*P38 -> 4200000000
B43: PPE Neta | D43: =D41-D42 -> 13200200000 | E43: =D43-E42 -> 12400400000 | F43: =E43-F42 -> 11600600000 | G43: =F43-G42 -> 10800800000 | H43: =G43-H42 -> 10001000000 | I43: =H43-I42 -> 9201200000 | J43: =I43-J42 -> 8401400000 | K43: =J43-K42 -> 7601600000 | L43: =K43-L42 -> 6801800000 | M43: =L43-M42 -> 6002000000 | O43: Valor en libros | P43: =M43 -> 6002000000
O44: Utilidad neta | P44: =P42-P43 -> -1802000000
B45: Capital Invertido en la operación | D45: =D43+D38 -> 1.2983712e+10 | E45: =E43+E38 -> 8.6898369e+09 | F45: =F43+F38 -> 7.2679328e+09 | G45: =G43+G38 -> 5.7712608e+09 | H45: =H43+H38 -> 4.1905993e+09 | I45: =I43+I38 -> 2.5172319e+09 | J45: =J43+J38 -> 7.5240568e+08 | K45: =K43+K38 -> -1.1336447e+09 | ... M45: =M43+M38 -> -5.3548079e+09 | O45: Impuesto por ganancia ocasional | P45: =IF(P44<0,0,P44*P40) -> 0
O47: Flujo de caja por venta del activo | P47: =P42-P45 -> 4200000000
B48: FLUJO DE CAJA | C48: Año 0 | D48: Año 1 | E48: Año 2 | F48: Año 3 | G48: Año 4 | H48: Año 5 | I48: Año 6 | J48: Año 7 | K48: Año 8 | L48: Año 9 | M48: Año 10 | N48: Año 11 | O48: Disposición final | P48: =Datos!$C$10*'Estado de resultados'!P39*1000000 -> 1470000000
B49: EBIT | D49: =D26 -> 1313450000 | E49: =E26 -> 13283005800 | F49: =F26 -> 1.5639437e+10 | G49: =G26 -> 1.8302934e+10 | H49: =H26 -> 2.1311823e+10 | I49: =I26 -> 2.4703327e+10 | J49: =J26 -> 2.8478557e+10 | K49: =K26 -> 3.2752901e+10 | ... M49: =M26 -> 4.3139978e+10 | O49: Valor de salvamento | P49: =P47-P48 -> 2730000000
B50: (-) Impuestos operativos | D50: =IF(D49<0,0,D49*D5) -> 459707500 | E50: =IF(E49<0,0,E49*E5) -> 4649052030 | F50: =IF(F49<0,0,F49*F5) -> 5.4738029e+09 | G50: =IF(G49<0,0,G49*G5) -> 6.4060269e+09 | H50: =IF(H49<0,0,H49*H5) -> 7.4591382e+09 | I50: =IF(I49<0,0,I49*I5) -> 8.6461644e+09 | J50: =IF(J49<0,0,J49*J5) -> 9.967495e+09 | K50: =IF(K49<0,0,K49*K5) -> 1.1463516e+10 | ... M50: =IF(M49<0,0,M49*M5) -> 1.5098992e+10
B51: NOPAT | D51: =D49-D50 -> 853742500 | E51: =E49-E50 -> 8633953770 | F51: =F49-F50 -> 1.0165634e+10 | G51: =G49-G50 -> 1.1896907e+10 | H51: =H49-H50 -> 1.3852685e+10 | I51: =I49-I50 -> 1.6057162e+10 | J51: =J49-J50 -> 1.8511062e+10 | K51: =K49-K50 -> 2.1289386e+10 | ... M51: =M49-M50 -> 2.8040986e+10
B52: Depreciaciones | D52: {=_xlfn.ANCHORARRAY(D22)} -> 799800000 | E52: 799800000 | F52: 799800000 | G52: 799800000 | H52: 799800000 | I52: 799800000 | J52: 799800000 | K52: 799800000 | L52: 799800000 | M52: 799800000
B53: Amortizaciones | D53: {=_xlfn.ANCHORARRAY(D23)} -> 0
B54: Flujo de caja bruto | D54: =D51+D52+D53 -> 1653542500 | E54: =E51+E52+E53 -> 9433753770 | F54: =F51+F52+F53 -> 1.0965434e+10 | G54: =G51+G52+G53 -> 1.2696707e+10 | H54: =H51+H52+H53 -> 1.4652485e+10 | I54: =I51+I52+I53 -> 1.6856962e+10 | J54: =J51+J52+J53 -> 1.9310862e+10 | K54: =K51+K52+K53 -> 2.2089186e+10 | ... M54: =M51+M52+M53 -> 2.8840786e+10
B57: FLUJO DE CAJA | C57: Año 0 | D57: Año 1 | E57: Año 2 | F57: Año 3 | G57: Año 4 | H57: Año 5 | I57: Año 6 | J57: Año 7 | K57: Año 8 | L57: Año 9 | M57: Año 10 | N57: Año 11
B58: EBITDA | D58: =D32 -> 2113250000 | E58: =E32 -> 14082805800 | F58: =F32 -> 1.6439237e+10 | G58: =G32 -> 1.9102734e+10 | H58: =H32 -> 2.2111623e+10 | I58: =I32 -> 2.5503127e+10 | J58: =J32 -> 2.9278357e+10 | K58: =K32 -> 3.3552701e+10 | ... M58: =M32 -> 4.3939778e+10
B59: (-) Impuestos operativos | D59: =D50 -> 459707500 | E59: =E50 -> 4649052030 | F59: =F50 -> 5.4738029e+09 | G59: =G50 -> 6.4060269e+09 | H59: =H50 -> 7.4591382e+09 | I59: =I50 -> 8.6461644e+09 | J59: =J50 -> 9.967495e+09 | K59: =K50 -> 1.1463516e+10 | ... M59: =M50 -> 1.5098992e+10
B60: Flujo de caja bruto | D60: =D58-D59 -> 1653542500 | E60: =E58-E59 -> 9433753770 | F60: =F58-F59 -> 1.0965434e+10 | G60: =G58-G59 -> 1.2696707e+10 | H60: =H58-H59 -> 1.4652485e+10 | I60: =I58-I59 -> 1.6856962e+10 | J60: =J58-J59 -> 1.9310862e+10 | K60: =K58-K59 -> 2.2089186e+10 | ... M60: =M58-M59 -> 2.8840786e+10
B61: (-) ΔKTNO | D61: =-D39 -> 2.1648808e+08 | E61: =-E39 -> 3.4940751e+09 | F61: =-F39 -> 6.22104e+08 | G61: =-G39 -> 6.9687201e+08 | H61: =-H39 -> 7.8086159e+08 | I61: =-I39 -> 8.7356733e+08 | J61: =-J39 -> 9.6502624e+08 | K61: =-K39 -> 1.0862503e+09 | ... M61: =-M39 -> 1.3899432e+09
B62: Flujo de caja operativo | D62: =D60+D61 -> 1.8700306e+09 | E62: =E54+E61 -> 1.2927829e+10 | F62: =F54+F61 -> 1.1587538e+10 | G62: =G54+G61 -> 1.3393579e+10 | H62: =H54+H61 -> 1.5433347e+10 | I62: =I54+I61 -> 1.773053e+10 | J62: =J54+J61 -> 2.0275888e+10 | K62: =K54+K61 -> 2.3175436e+10 | L62: =L54+L61 -> 2.648692e+10 | M62: =M54+M61 -> 3.0230729e+10
B63: (-) CAPEX | C63: =-Datos!C10*1000000 -> -14000000000 | D63: 0 | E63: 0 | F63: 0 | G63: 0 | H63: =-Datos!$C$10*Datos!$C$24*1000000 -> -9800000000 | I63: 0 | J63: 0 | K63: 0 | L63: 0 | M63: 0
B64: FCL (Unlevered cash flow) | C64: =C62+C63 -> -14000000000 | D64: =D62+D63 -> 1.8700306e+09 | E64: =E62+E63 -> 1.2927829e+10 | F64: =F62+F63 -> 1.1587538e+10 | G64: =G62+G63 -> 1.3393579e+10 | H64: =H62+H63 -> 5.6333468e+09 | I64: =I62+I63 -> 1.773053e+10 | J64: =J62+J63 -> 2.0275888e+10 | ... M64: =M62+M63 -> 3.0230729e+10 | N64: =P49 -> 2730000000
B65: Factor de descuento | D65: =1/(1+WACC!$B$18)^'Estado de resultados'!D2 -> 0.83064215 | E65: =1/(1+WACC!$B$18)^'Estado de resultados'!E2 -> 0.68996639 | F65: =1/(1+WACC!$B$18)^'Estado de resultados'!F2 -> 0.57311517 | G65: =1/(1+WACC!$B$18)^'Estado de resultados'!G2 -> 0.47605362 | H65: =1/(1+WACC!$B$18)^'Estado de resultados'!H2 -> 0.3954302 | I65: =1/(1+WACC!$B$18)^'Estado de resultados'!I2 -> 0.32846099 | J65: =1/(1+WACC!$B$18)^'Estado de resultados'!J2 -> 0.27283355 | K65: =1/(1+WACC!$B$18)^'Estado de resultados'!K2 -> 0.22662705 | ... M65: =1/(1+WACC!$B$18)^'Estado de resultados'!M2 -> 0.15636504 | N65: =1/(1+WACC!$B$18)^11 -> 0.1298834
B66: FCL descontado | C66: =C64 -> -14000000000 | D66: =D64*D65 -> 1.5533262e+09 | E66: =E64*E65 -> 8.9197674e+09 | F66: =F64*F65 -> 6.6409938e+09 | G66: =G64*G65 -> 6.3760618e+09 | H66: =H64*H65 -> 2.2275955e+09 | I66: =I64*I65 -> 5.8237874e+09 | J66: =J64*J65 -> 5.5319426e+09 | K66: =K64*K65 -> 5.2521807e+09 | ... N66: =N64*N65 -> 3.5458167e+08
B67: Δ Deuda | D67: =D91 -> 8400000000 | E67: =E91-D91 -> -840000000 | F67: =F91-E91 -> -840000000 | G67: =G91-F91 -> -840000000 | H67: =H91-G91 -> -840000000 | I67: =I91-H91 -> -840000000 | J67: =J91-I91 -> -840000000 | K67: =K91-J91 -> -840000000 | L67: =L91-K91 -> -840000000 | M67: =M91-L91 -> -1680000000
B68: Equity Cash Flow | D68: =D64+D67-D27*(1-D5) -> 1.021298e+10 | E68: =E64+E67-E27*(1-E5) -> 1.1978007e+10 | F68: =F64+F67-F27*(1-F5) -> 1.0649126e+10 | G68: =G64+G67-G27*(1-G5) -> 1.2466577e+10 | H68: =H64+H67-H27*(1-H5) -> 4.7177551e+09 | I68: =I64+I67-I27*(1-I5) -> 1.6826348e+10 | J68: =J64+J67-J27*(1-J5) -> 1.9383117e+10 | K68: =K64+K67-K27*(1-K5) -> 2.2294075e+10 | ... M68: =M64+M67-M27*(1-M5) -> 2.8536467e+10
B71: VPN del Proyecto | C71: =NPV(WACC!B18,'Estado de resultados'!D64:N64)+'Estado de resultados'!C64 -> 3.8393322e+10
B72: TIR Modificada | C72: =MIRR(C64:N64,WACC!B18,WACC!B18) -> 0.35734544
B73: PAYBACK Ajustado | C73: =2+ABS(SUM(C66:E66))/F66 -> 2.5310811
B74: FD
B75: FCL Descontado
B76: Profitability Index | C76: =ABS(SUM(D66:N66)/C64) -> 3.7423802
B79: ROIC | D79: =D51/D45 -> 0.065754886 | E79: =E51/E45 -> 0.99356914 | F79: =F51/F45 -> 1.3986967 | G79: =G51/G45 -> 2.0614052 | H79: =H51/H45 -> 3.3056573 | I79: =I51/I45 -> 6.3788967 | J79: =J51/J45 -> 24.602502 | K79: =K51/K45 -> -18.779593 | ... M79: =M51/M45 -> -5.2365998
B80: Margen bruto | D80: =D19/D15 -> 0.66807692 | E80: =E19/E15 -> 0.69942671 | F80: =F19/F15 -> 0.70885793 | G80: =G19/G15 -> 0.71792396 | H80: =H19/H15 -> 0.7266391 | I80: =I19/I15 -> 0.73501709 | J80: =J19/J15 -> 0.74307112 | K80: =K19/K15 -> 0.75081385 | ... M80: =M19/M15 -> 0.76541363
B81: Margen EBIT | D81: =D26/D15 -> 0.13471282 | E81: =E26/E15 -> 0.36429843 | F81: =F26/F15 -> 0.37874099 | G81: =G26/G15 -> 0.39233796 | H81: =H26/H15 -> 0.40516806 | I81: =I26/I15 -> 0.41729377 | J81: =J26/J15 -> 0.42875353 | K81: =K26/K15 -> 0.43962908 | ... M81: =M26/M15 -> 0.45978945
B82: Margen EBITDA | D82: =D32/D15 -> 0.21674359 | E82: =E32/E15 -> 0.38623367 | F82: =F32/F15 -> 0.39810978 | G82: =G32/G15 -> 0.40948231 | H82: =H32/H15 -> 0.42037339 | I82: =I32/I15 -> 0.43080416 | J82: =J32/J15 -> 0.44079477 | K82: =K32/K15 -> 0.45036447 | ... M82: =M32/M15 -> 0.46831378
B83: Margen KTNO (Productividad del capital de trabajo) | D83: =D38/D15 -> -0.022203906 | E83: =E38/E15 -> -0.10176555 | F83: =F38/F15 -> -0.10492441 | G83: =G38/G15 -> -0.10781218 | H83: =H38/H15 -> -0.11046398 | I83: =I38/I15 -> -0.11290699 | J83: =J38/J15 -> -0.11515799 | K83: =K38/K15 -> -0.11724969 | ... M83: =M38/M15 -> -0.12104179
B85: Palanca de crecimiento | D85: =D82/D83 -> -9.7615074 | E85: =E82/E83 -> -3.7953284 | F85: =F82/F83 -> -3.7942534 | G85: =G82/G83 -> -3.7981082 | H85: =H82/H83 -> -3.8055247 | I85: =I82/I83 -> -3.8155668 | J85: =J82/J83 -> -3.8277394 | K85: =K82/K83 -> -3.8410717 | ... M85: =M82/M83 -> -3.8690254
B86: EVA | D86: =(D79-WACC!$B$18)*'Estado de resultados'!D45 -> -1.7934787e+09 | E86: =(E79-WACC!$B$18)*'Estado de resultados'!E45 -> 6.8622016e+09 | F86: =(F79-WACC!$B$18)*'Estado de resultados'!F45 -> 8.6837907e+09 | G86: =(G79-WACC!$B$18)*'Estado de resultados'!G45 -> 1.0720217e+10 | H86: =(H79-WACC!$B$18)*'Estado de resultados'!H45 -> 1.2998273e+10 | I86: =(I79-WACC!$B$18)*'Estado de resultados'!I45 -> 1.5543929e+10 | J86: =(J79-WACC!$B$18)*'Estado de resultados'!J45 -> 1.8357656e+10 | K86: =(K79-WACC!$B$18)*'Estado de resultados'!K45 -> 2.1520522e+10 | ... M86: =(M79-WACC!$B$18)*'Estado de resultados'!M45 -> 2.9132766e+10
B88: Razón de cobertura de intereses (EBIT / gastos financieros) | D88: =D26/D27 -> 14.96472 | E88: =E26/E27 -> 78.617761 | F88: =F26/F27 -> 103.29684 | G88: =G26/G27 -> 136.74326 | H88: =H26/H27 -> 183.25666 | I88: =I26/I27 -> 250.1831 | J88: =J26/J27 -> 350.77715 | K88: =K26/K27 -> 514.71499 | ... M88: =M26/M27 -> 1966.0518
B89: Servicio a la deuda | D89: {=TRANSPOSE(Bancos!L20:L29)*1000000} -> 1.7553954e+09 | E89: 2.5295681e+09 | F89: 2.3540285e+09 | G89: 2.178489e+09 | H89: 2.0029494e+09 | I89: 1.8274099e+09 | J89: 1.6518704e+09 | K89: 1.4763308e+09 | L89: 1.3007913e+09 | M89: 1.8994244e+09
B90: Debt Service Coverage Ratio (FCL / Servicio a la deuda) | D90: =D62/D89 -> 1.0653045 | E90: =E62/E89 -> 5.1106863 | F90: =F62/F89 -> 4.9224289 | G90: =G62/G89 -> 6.1481051 | H90: =H62/H89 -> 7.7053102 | I90: =I62/I89 -> 9.7025466 | J90: =J62/J89 -> 12.274503 | K90: =K62/K89 -> 15.697997 | ... M90: =M62/M89 -> 15.915732
B91: Deuda | D91: {=TRANSPOSE(Bancos!M20:M29)*1000000} -> 8400000000 | E91: 7560000000 | F91: 6720000000 | G91: 5880000000 | H91: 5040000000 | I91: 4200000000 | J91: 3360000000 | K91: 2520000000 | L91: 1680000000 | M91: 0
B92: Apalancamiento financiero (Deuda / EBITDA) | D92: =D91/D32 -> 3.9749201 | E92: =E91/E32 -> 0.53682484 | F92: =F91/F32 -> 0.4087781 | G92: =G91/G32 -> 0.30780934 | H92: =H91/H32 -> 0.22793442 | I92: =I91/I32 -> 0.16468569 | J92: =J91/J32 -> 0.11476054 | K92: =K91/K32 -> 0.075105726 | ... M92: =M91/M32 -> 0
B93: CAGR

Sheet Breakeven Precio
B1: Año | C1: Año 0 | D1: Año 1 | E1: Año 2 | F1: Año 3 | G1: Año 4 | H1: Año 5 | I1: Año 6 | J1: Año 7 | K1: Año 8 | L1: Año 9 | M1: Año 10
B2: Consecutivo | C2: 0 | D2: 1 | E2: 2 | F2: 3 | G2: 4 | H2: 5 | I2: 6 | J2: 7 | K2: 8 | L2: 9 | M2: 10
B4: Inflación | D4: 0.0584 | E4: 0.0684 | F4: 0.0658 | G4: 0.0637 | H4: 0.06175 | I4: 0.0585 | J4: 0.05815 | K4: 0.0588 | L4: 0.0586 | M4: 0.0585
B5: Tasa de impuestos | D5: 0.35 | E5: 0.35 | F5: 0.35 | G5: 0.35 | H5: 0.35 | I5: 0.35 | J5: 0.35 | K5: 0.35 | L5: 0.35 | M5: 0.35
B8: Precio | C8: =(D8-'Estado de resultados'!D8)/'Estado de resultados'!D8 -> 0.49806619 | D8: 9737430.2 | E8: =D8*(1+D4)*(1+Datos!$C$31) -> 10924462 | F8: =E8*(1+E4)*(1+Datos!$C$31) -> 12371997 | G8: =F8*(1+F4)*(1+Datos!$C$31) -> 13977239 | H8: =G8*(1+G4)*(1+Datos!$C$31) -> 15759644 | I8: =H8*(1+H4)*(1+Datos!$C$31) -> 17736770 | J8: =I8*(1+I4)*(1+Datos!$C$31) -> 19900834 | K8: =J8*(1+J4)*(1+Datos!$C$31) -> 22321551 | L8: =K8*(1+K4)*(1+Datos!$C$31) -> 25052102 | M8: =L8*(1+L4)*(1+Datos!$C$31) -> 28111364
B9: Costo | D9: 2000000 | E9: =D9*(1+D4)*(1+Datos!$C$23) -> 2159136 | F9: =E9*(1+E4)*(1+Datos!$C$23) -> 2352957.3 | G9: =F9*(1+F4)*(1+Datos!$C$23) -> 2557937.6 | H9: =G9*(1+G4)*(1+Datos!$C$23) -> 2775295.7 | I9: =H9*(1+H4)*(1+Datos!$C$23) -> 3005603.7 | J9: =I9*(1+I4)*(1+Datos!$C$23) -> 3245060.1 | K9: =J9*(1+J4)*(1+Datos!$C$23) -> 3502435.5 | L9: =K9*(1+K4)*(1+Datos!$C$23) -> 3782546.3 | M9: =L9*(1+L4)*(1+Datos!$C$23) -> 4084287.6
B10: Cantidades | D10: 1000 | E10: 1000 | F10: 1000 | G10: 1500 | H10: 1500 | I10: 1500 | J10: 2500 | K10: 2500 | L10: 2500 | M10: 2500
B14: ESTADO DE RESULTADOS | C14: Año 0 | D14: Año 1 | E14: Año 2 | F14: Año 3 | G14: Año 4 | H14: Año 5 | I14: Año 6 | J14: Año 7 | K14: Año 8 | L14: Año 9 | M14: Año 10 | N14: Año 11
A15: =D15/$D$15 -> 1 | B15: Ingresos operacionales | D15: =D8*D10 -> 9.7374302e+09 | E15: =E8*E10 -> 1.0924462e+10 | F15: =F8*F10 -> 1.2371997e+10 | G15: =G8*G10 -> 2.0965858e+10 | H15: =H8*H10 -> 2.3639466e+10 | I15: =I8*I10 -> 2.6605155e+10 | J15: =J8*J10 -> 4.9752084e+10 | K15: =K8*K10 -> 5.5803878e+10 | ... M15: =M8*M10 -> 7.0278411e+10
A16: =D16/$D$15 -> 0.205393 | B16: Costo de ventas | D16: =D9*D10 -> 2000000000 | E16: =E9*E10 -> 2159136000 | F16: =F9*F10 -> 2.3529573e+09 | G16: =G9*G10 -> 3.8369063e+09 | H16: =H9*H10 -> 4.1629436e+09 | I16: =I9*I10 -> 4.5084055e+09 | J16: =J9*J10 -> 8.1126502e+09 | K16: =K9*K10 -> 8.7560889e+09 | ... M16: =M9*M10 -> 1.0210719e+10
A17: =D17/$D$15 -> 0.03080895 | B17: Costo de nómina asociada a la operación | D17: =Nómina!H3 -> 300000000 | E17: =D17*(1+D4) -> 317520000 | F17: =E17*(1+E4) -> 339238368 | G17: =F17*(1+F4) -> 3.6156025e+08 | H17: =G17*(1+G4) -> 3.8459164e+08 | I17: =H17*(1+H4) -> 4.0834017e+08 | J17: =I17*(1+I4) -> 4.3222807e+08 | K17: =J17*(1+J4) -> 4.5736214e+08 | L17: =K17*(1+K4) -> 4.8425503e+08 | M17: =L17*(1+L4) -> 5.1263238e+08
A18: =D18/$D$15 -> 0.055 | B18: Costo de mantenimiento | D18: =D15*Datos!$C$21 -> 5.3555866e+08 | E18: =E15*Datos!$C$21 -> 6.0084541e+08 | F18: =F15*Datos!$C$21 -> 6.8045983e+08 | G18: =G15*Datos!$C$21 -> 1.1531222e+09 | H18: =H15*Datos!$C$21 -> 1.3001706e+09 | I18: =I15*Datos!$C$21 -> 1.4632835e+09 | J18: =J15*Datos!$C$21 -> 2.7363646e+09 | K18: =K15*Datos!$C$21 -> 3.0692133e+09 | ... M18: =M15*Datos!$C$21 -> 3.8653126e+09
A19: =D19/$D$15 -> 0.70879805 | B19: Utilidad bruta | D19: =D15-D16-D17-D18 -> 6.9018716e+09 | E19: =E15-E16-E17-E18 -> 7.8469605e+09 | F19: =F15-F16-F17-F18 -> 8.9993413e+09 | G19: =G15-G16-G17-G18 -> 1.5614269e+10 | H19: =H15-H16-H17-H18 -> 1.779176e+10 | I19: =I15-I16-I17-I18 -> 2.0225126e+10 | J19: =J15-J16-J17-J18 -> 3.8470841e+10 | K19: =K15-K16-K17-K18 -> 4.3521214e+10 | ... M19: =M15-M16-M17-M18 -> 5.5689747e+10
A20: =D20/$D$15 -> 0.15281239 | B20: Costos de nómina administrativos | D20: =Nómina!H4 -> 1488000000 | E20: =D20*(1+D4) -> 1574899200 | F20: =E20*(1+E4) -> 1.6826223e+09 | G20: =F20*(1+F4) -> 1.7933389e+09 | H20: =G20*(1+G4) -> 1.9075745e+09 | I20: =H20*(1+H4) -> 2.0253673e+09 | J20: =I20*(1+I4) -> 2.1438513e+09 | K20: =J20*(1+J4) -> 2.2685162e+09 | L20: =K20*(1+K4) -> 2.401905e+09 | M20: =L20*(1+L4) -> 2.5426566e+09
A21: =D21/$D$15 -> 0.25 | B21: Gastos operacionales (variable) | D21: =D15*Datos!$C$26 -> 2.4343576e+09 | E21: =E15*Datos!$C$26 -> 2.7311155e+09 | F21: =F15*Datos!$C$26 -> 3.0929992e+09 | G21: =G15*Datos!$C$26 -> 5.2414645e+09 | H21: =H15*Datos!$C$26 -> 5.9098665e+09 | I21: =I15*Datos!$C$26 -> 6.6512889e+09 | J21: =J15*Datos!$C$26 -> 1.2438021e+10 | K21: =K15*Datos!$C$26 -> 1.3950969e+10 | ... M21: =M15*Datos!$C$26 -> 1.7569603e+10
A22: =D22/$D$15 -> 0.08213666 | B22: Depreciación | D22: {=Depreciaciones!B7:K7} -> 799800000 | E22: 799800000 | F22: 799800000 | G22: 799800000 | H22: 799800000 | I22: 799800000 | J22: 799800000 | K22: 799800000 | L22: 799800000 | M22: 799800000
A23: =D23/$D$15 -> 0.02875502 | B23: Amortización | D23: {='Amortización gasto seguro'!B4:K4} -> 280000000 | E23: 280000000 | F23: 280000000 | G23: 280000000 | H23: 280000000 | I23: 280000000 | J23: 280000000 | K23: 280000000 | L23: 280000000 | M23: 280000000
A24: =D24/$D$15 -> 0.02 | B24: Comisiones | D24: =D15*Datos!$C$27 -> 1.947486e+08 | E24: =E15*Datos!$C$27 -> 2.1848924e+08 | F24: =F15*Datos!$C$27 -> 2.4743994e+08 | G24: =G15*Datos!$C$27 -> 4.1931716e+08 | H24: =H15*Datos!$C$27 -> 4.7278932e+08 | I24: =I15*Datos!$C$27 -> 5.3210311e+08 | J24: =J15*Datos!$C$27 -> 9.9504168e+08 | K24: =K15*Datos!$C$27 -> 1.1160776e+09 | ... M24: =M15*Datos!$C$27 -> 1.4055682e+09
A25: =D25/$D$15 -> 0.17509398 | B25: EBIT | D25: =D19-D20-D21-D22-D23-D24 -> 1.7049654e+09 | E25: =E19-E20-E21-E22-E23-E24 -> 2.2426566e+09 | F25: =F19-F20-F21-F22-F23-F24 -> 2.8964799e+09 | G25: =G19-G20-G21-G22-G23-G24 -> 7.0803487e+09 | H25: =H19-H20-H21-H22-H23-H24 -> 8.4217299e+09 | I25: =I19-I20-I21-I22-I23-I24 -> 9.936567e+09 | J25: =J19-J20-J21-J22-J23-J24 -> 2.1814127e+10 | K25: =K19-K20-K21-K22-K23-K24 -> 2.510585e+10 | ... M25: =M19-M20-M21-M22-M23-M24 -> 3.3092119e+10
A26: =D26/$D$15 -> 0.18027296 | B26: Gastos financieros (intereses) | D26: {=TRANSPOSE(Bancos!L20:L29)*1000000} -> 1.7553954e+09 | E26: 2.5295681e+09 | F26: 2.3540285e+09 | G26: 2.178489e+09 | H26: 2.0029494e+09 | I26: 1.8274099e+09 | J26: 1.6518704e+09 | K26: 1.4763308e+09 | L26: 1.3007913e+09 | M26: 1.8994244e+09
A27: =D27/$D$15 -> -0.0051789811 | B27: EBT | D27: =D25-D26 -> -50429967 | E27: =E25-E26 -> -2.8691145e+08 | F27: =F25-F26 -> 5.4245136e+08 | G27: =G25-G26 -> 4.9018598e+09 | H27: =H25-H26 -> 6.4187805e+09 | I27: =I25-I26 -> 8.1091571e+09 | J27: =J25-J26 -> 2.0162257e+10 | K27: =K25-K26 -> 2.3629519e+10 | ... M27: =M25-M26 -> 3.1192695e+10
A28: =D28/$D$15 -> 0 | B28: Provisión de impuestos | D28: =IF(D27<0,0,D27*D5) -> 0 | E28: =IF(E27<0,0,E27*E5) -> 0 | F28: =IF(F27<0,0,F27*F5) -> 1.8985798e+08 | G28: =IF(G27<0,0,G27*G5) -> 1.7156509e+09 | H28: =IF(H27<0,0,H27*H5) -> 2.2465732e+09 | I28: =IF(I27<0,0,I27*I5) -> 2.838205e+09 | J28: =IF(J27<0,0,J27*J5) -> 7.0567899e+09 | K28: =IF(K27<0,0,K27*K5) -> 8.2703318e+09 | ... M28: =IF(M27<0,0,M27*M5) -> 1.0917443e+10
A29: =D29/$D$15 -> -0.0051789811 | B29: Utilidad neta | D29: =D27-D28 -> -50429967 | E29: =E27-E28 -> -2.8691145e+08 | F29: =F27-F28 -> 3.5259338e+08 | G29: =G27-G28 -> 3.1862088e+09 | H29: =H27-H28 -> 4.1722073e+09 | I29: =I27-I28 -> 5.2709521e+09 | J29: =J27-J28 -> 1.3105467e+10 | K29: =K27-K28 -> 1.5359188e+10 | ... M29: =M27-M28 -> 2.0275252e+10
B31: EBITDA | D31: =D25+D22+D23 -> 2.7847654e+09 | E31: =E25+E22+E23 -> 3.3224566e+09 | F31: =F25+F22+F23 -> 3.9762799e+09 | G31: =G25+G22+G23 -> 8.1601487e+09 | H31: =H25+H22+H23 -> 9.5015299e+09 | I31: =I25+I22+I23 -> 1.1016367e+10 | J31: =J25+J22+J23 -> 2.2893927e+10 | K31: =K25+K22+K23 -> 2.618565e+10 | ... M31: =M25+M22+M23 -> 3.4171919e+10
A33: =D33/$D$15 -> 0.083333333 | B33: CXC | D33: =(Datos!$C$28/360)*'Breakeven Precio'!D15 -> 8.1145252e+08 | E33: =(Datos!$C$28/360)*'Breakeven Precio'!E15 -> 9.1037183e+08 | F33: =(Datos!$C$28/360)*'Breakeven Precio'!F15 -> 1.0309997e+09 | G33: =(Datos!$C$28/360)*'Breakeven Precio'!G15 -> 1.7471548e+09 | H33: =(Datos!$C$28/360)*'Breakeven Precio'!H15 -> 1.9699555e+09 | I33: =(Datos!$C$28/360)*'Breakeven Precio'!I15 -> 2.2170963e+09 | J33: =(Datos!$C$28/360)*'Breakeven Precio'!J15 -> 4.146007e+09 | K33: =(Datos!$C$28/360)*'Breakeven Precio'!K15 -> 4.6503231e+09 | ... M33: =(Datos!$C$28/360)*'Breakeven Precio'!M15 -> 5.8565342e+09
B34: KTO | D34: =D33 -> 8.1145252e+08 | E34: =E33 -> 9.1037183e+08 | F34: =F33 -> 1.0309997e+09 | G34: =G33 -> 1.7471548e+09 | H34: =H33 -> 1.9699555e+09 | I34: =I33 -> 2.2170963e+09 | J34: =J33 -> 4.146007e+09 | K34: =K33 -> 4.6503231e+09 | ... M34: =M33 -> 5.8565342e+09
A35: =D35/$D$15 -> 0.05134825 | B35: CXP | D35: =(Datos!$C$29/360)*'Breakeven Precio'!D16 -> 500000000 | E35: =(Datos!$C$29/360)*'Breakeven Precio'!E16 -> 539784000 | F35: =(Datos!$C$29/360)*'Breakeven Precio'!F16 -> 5.8823933e+08 | G35: =(Datos!$C$29/360)*'Breakeven Precio'!G16 -> 9.5922658e+08 | H35: =(Datos!$C$29/360)*'Breakeven Precio'!H16 -> 1.0407359e+09 | I35: =(Datos!$C$29/360)*'Breakeven Precio'!I16 -> 1.1271014e+09 | J35: =(Datos!$C$29/360)*'Breakeven Precio'!J16 -> 2.0281626e+09 | K35: =(Datos!$C$29/360)*'Breakeven Precio'!K16 -> 2.1890222e+09 | ... M35: =(Datos!$C$29/360)*'Breakeven Precio'!M16 -> 2.5526798e+09
A36: =D36/$D$15 -> 0 | B36: Impuestos por pagar | D36: =D28 -> 0 | E36: =E28 -> 0 | F36: =F28 -> 1.8985798e+08 | G36: =G28 -> 1.7156509e+09 | H36: =H28 -> 2.2465732e+09 | I36: =I28 -> 2.838205e+09 | J36: =J28 -> 7.0567899e+09 | K36: =K28 -> 8.2703318e+09 | ... M36: =M28 -> 1.0917443e+10
B37: KTNO | D37: =D34-D35-D36 -> 3.1145252e+08 | E37: =E34-E35-E36 -> 3.7058783e+08 | F37: =F34-F35-F36 -> 2.5290243e+08 | G37: =G34-G35-G36 -> -9.2772266e+08 | H37: =H34-H35-H36 -> -1.3173535e+09 | I37: =I34-I35-I36 -> -1.7482101e+09 | J37: =J34-J35-J36 -> -4.9389454e+09 | K37: =K34-K35-K36 -> -5.8090309e+09 | ... M37: =M34-M35-M36 -> -7.6135887e+09 | O37: Proyección venta de activos | P37: 0.3
B38: Δ KTNO | D38: =D37 -> 3.1145252e+08 | E38: =E37-D37 -> 59135308 | F38: =F37-E37 -> -1.176854e+08 | G38: =G37-F37 -> -1.1806251e+09 | H38: =H37-G37 -> -3.8963088e+08 | I38: =I37-H37 -> -4.3085652e+08 | J38: =J37-I37 -> -3.1907354e+09 | K38: =K37-J37 -> -8.7008545e+08 | L38: =L37-K37 -> -9.7917935e+08 | M38: =M37-L37 -> -8.2537849e+08 | O38: Costo de desmantelamiento | P38: 0.105
O39: Tasa de impuesto por ganancia ocasional | P39: 0.15
B40: PPE (Propiedades, Planta y Equipo) Bruta | C40: =Datos!C10*1000000 -> 14000000000 | D40: =C40 -> 14000000000 | E40: =D40 -> 14000000000 | F40: =E40 -> 14000000000 | G40: =F40 -> 14000000000 | H40: =G40 -> 14000000000 | I40: =H40 -> 14000000000 | J40: =I40 -> 14000000000 | K40: =J40 -> 14000000000 | ... M40: =L40 -> 14000000000
B41: Depreciación acumulada | D41: =D22 -> 799800000 | E41: =E22 -> 799800000 | F41: =F22 -> 799800000 | G41: =G22 -> 799800000 | H41: =H22 -> 799800000 | I41: =I22 -> 799800000 | J41: =J22 -> 799800000 | K41: =K22 -> 799800000 | ... M41: =M22 -> 799800000 | O41: Valor en venta esperado | P41: =Datos!$C$10*1000000*P37 -> 4200000000
B42: PPE Neta | D42: =D40-D41 -> 13200200000 | E42: =D42-E41 -> 12400400000 | F42: =E42-F41 -> 11600600000 | G42: =F42-G41 -> 10800800000 | H42: =G42-H41 -> 10001000000 | I42: =H42-I41 -> 9201200000 | J42: =I42-J41 -> 8401400000 | K42: =J42-K41 -> 7601600000 | L42: =K42-L41 -> 6801800000 | M42: =L42-M41 -> 6002000000 | O42: Valor en libros | P42: =M42 -> 6002000000
O43: Utilidad neta | P43: =P41-P42 -> -1802000000
B44: Capital Invertido en la operación | D44: =D42+D37 -> 1.3511653e+10 | E44: =E42+E37 -> 1.2770988e+10 | F44: =F42+F37 -> 1.1853502e+10 | G44: =G42+G37 -> 9.8730773e+09 | H44: =H42+H37 -> 8.6836465e+09 | I44: =I42+I37 -> 7.4529899e+09 | J44: =J42+J37 -> 3.4624546e+09 | K44: =K42+K37 -> 1.7925691e+09 | ... M44: =M42+M37 -> -1.6115887e+09 | O44: Impuesto por ganancia ocasional | P44: =IF(P43<0,0,P43*P39) -> 0
O46: Flujo de caja por venta del activo | P46: =P41-P44 -> 4200000000
B47: FLUJO DE CAJA | C47: Año 0 | D47: Año 1 | E47: Año 2 | F47: Año 3 | G47: Año 4 | H47: Año 5 | I47: Año 6 | J47: Año 7 | K47: Año 8 | L47: Año 9 | M47: Año 10 | N47: Año 11 | O47: Disposición final | P47: =Datos!$C$10*'Breakeven Precio'!P38*1000000 -> 1470000000
B48: EBIT | D48: =D25 -> 1.7049654e+09 | E48: =E25 -> 2.2426566e+09 | F48: =F25 -> 2.8964799e+09 | G48: =G25 -> 7.0803487e+09 | H48: =H25 -> 8.4217299e+09 | I48: =I25 -> 9.936567e+09 | J48: =J25 -> 2.1814127e+10 | K48: =K25 -> 2.510585e+10 | ... M48: =M25 -> 3.3092119e+10 | O48: Valor de salvamento | P48: =P46-P47 -> 2730000000
B49: (-) Impuestos operativos | D49: =IF(D48<0,0,D48*D5) -> 5.9673789e+08 | E49: =IF(E48<0,0,E48*E5) -> 7.8492981e+08 | F49: =IF(F48<0,0,F48*F5) -> 1.013768e+09 | G49: =IF(G48<0,0,G48*G5) -> 2.4781221e+09 | H49: =IF(H48<0,0,H48*H5) -> 2.9476055e+09 | I49: =IF(I48<0,0,I48*I5) -> 3.4777984e+09 | J49: =IF(J48<0,0,J48*J5) -> 7.6349445e+09 | K49: =IF(K48<0,0,K48*K5) -> 8.7870476e+09 | ... M49: =IF(M48<0,0,M48*M5) -> 1.1582242e+10
B50: NOPAT | D50: =D48-D49 -> 1.1082275e+09 | E50: =E48-E49 -> 1.4577268e+09 | F50: =F48-F49 -> 1.8827119e+09 | G50: =G48-G49 -> 4.6022267e+09 | H50: =H48-H49 -> 5.4741244e+09 | I50: =I48-I49 -> 6.4587685e+09 | J50: =J48-J49 -> 1.4179183e+10 | K50: =K48-K49 -> 1.6318803e+10 | ... M50: =M48-M49 -> 2.1509878e+10
B51: Depreciaciones | D51: {=_xlfn.ANCHORARRAY(D22)} -> 799800000 | E51: 799800000 | F51: 799800000 | G51: 799800000 | H51: 799800000 | I51: 799800000 | J51: 799800000 | K51: 799800000 | L51: 799800000 | M51: 799800000
B52: Amortizaciones | D52: {=_xlfn.ANCHORARRAY(D23)} -> 280000000 | E52: 280000000 | F52: 280000000 | G52: 280000000 | H52: 280000000 | I52: 280000000 | J52: 280000000 | K52: 280000000 | L52: 280000000 | M52: 280000000
B53: Flujo de caja bruto | D53: =D50+D51+D52 -> 2.1880275e+09 | E53: =E50+E51+E52 -> 2.5375268e+09 | F53: =F50+F51+F52 -> 2.9625119e+09 | G53: =G50+G51+G52 -> 5.6820267e+09 | H53: =H50+H51+H52 -> 6.5539244e+09 | I53: =I50+I51+I52 -> 7.5385685e+09 | J53: =J50+J51+J52 -> 1.5258983e+10 | K53: =K50+K51+K52 -> 1.7398603e+10 | ... M53: =M50+M51+M52 -> 2.2589678e+10
B56: FLUJO DE CAJA | C56: Año 0 | D56: Año 1 | E56: Año 2 | F56: Año 3 | G56: Año 4 | H56: Año 5 | I56: Año 6 | J56: Año 7 | K56: Año 8 | L56: Año 9 | M56: Año 10 | N56: Año 11
B57: EBITDA | D57: =D31 -> 2.7847654e+09 | E57: =E31 -> 3.3224566e+09 | F57: =F31 -> 3.9762799e+09 | G57: =G31 -> 8.1601487e+09 | H57: =H31 -> 9.5015299e+09 | I57: =I31 -> 1.1016367e+10 | J57: =J31 -> 2.2893927e+10 | K57: =K31 -> 2.618565e+10 | ... M57: =M31 -> 3.4171919e+10
B58: (-) Impuestos operativos | D58: =D49 -> 5.9673789e+08 | E58: =E49 -> 7.8492981e+08 | F58: =F49 -> 1.013768e+09 | G58: =G49 -> 2.4781221e+09 | H58: =H49 -> 2.9476055e+09 | I58: =I49 -> 3.4777984e+09 | J58: =J49 -> 7.6349445e+09 | K58: =K49 -> 8.7870476e+09 | ... M58: =M49 -> 1.1582242e+10
B59: Flujo de caja bruto | D59: =D57-D58 -> 2.1880275e+09 | E59: =E57-E58 -> 2.5375268e+09 | F59: =F57-F58 -> 2.9625119e+09 | G59: =G57-G58 -> 5.6820267e+09 | H59: =H57-H58 -> 6.5539244e+09 | I59: =I57-I58 -> 7.5385685e+09 | J59: =J57-J58 -> 1.5258983e+10 | K59: =K57-K58 -> 1.7398603e+10 | ... M59: =M57-M58 -> 2.2589678e+10
B60: (-) ΔKTNO | D60: =-D38 -> -3.1145252e+08 | E60: =-E38 -> -59135308 | F60: =-F38 -> 1.176854e+08 | G60: =-G38 -> 1.1806251e+09 | H60: =-H38 -> 3.8963088e+08 | I60: =-I38 -> 4.3085652e+08 | J60: =-J38 -> 3.1907354e+09 | K60: =-K38 -> 8.7008545e+08 | ... M60: =-M38 -> 8.2537849e+08
B61: Flujo de Caja Libre | D61: =D59+D60 -> 1.876575e+09 | E61: =E53+E60 -> 2.4783915e+09 | F61: =F53+F60 -> 3.0801973e+09 | G61: =G53+G60 -> 6.8626518e+09 | H61: =H53+H60 -> 6.9435553e+09 | I61: =I53+I60 -> 7.9694251e+09 | J61: =J53+J60 -> 1.8449718e+10 | K61: =K53+K60 -> 1.8268688e+10 | L61: =L53+L60 -> 2.0813492e+10 | M61: =M53+M60 -> 2.3415056e+10
B62: (-) CAPEX | C62: =-Datos!C10*1000000 -> -14000000000 | D62: 0 | E62: 0 | F62: 0 | G62: 0 | H62: =-Datos!$C$10*Datos!$C$24*1000000 -> -9800000000 | I62: 0 | J62: 0 | K62: 0 | L62: 0 | M62: 0
B63: FCL (Unlevered cash flow) | C63: =C61+C62 -> -14000000000 | D63: =D61+D62 -> 1.876575e+09 | E63: =E61+E62 -> 2.4783915e+09 | F63: =F61+F62 -> 3.0801973e+09 | G63: =G61+G62 -> 6.8626518e+09 | H63: =H61+H62 -> -2.8564447e+09 | I63: =I61+I62 -> 7.9694251e+09 | J63: =J61+J62 -> 1.8449718e+10 | ... M63: =M61+M62 -> 2.3415056e+10 | N63: =P48 -> 2730000000
B66: VPN del Proyecto | C66: =NPV(WACC!B18,'Breakeven Precio'!D63:N63)+'Breakeven Precio'!C63 -> 1.2897003e+10
B67: TIR Modificada | C67: =MIRR(C63:N63,WACC!B18,WACC!B18) -> 0.27328727
B68: PAYBACK Ajustado | C68: 0
B69: FD | D69: =1/(1+WACC!$B$18)^'Breakeven Precio'!D2 -> 0.83064215 | E69: =1/(1+WACC!$B$18)^'Breakeven Precio'!E2 -> 0.68996639 | F69: =1/(1+WACC!$B$18)^'Breakeven Precio'!F2 -> 0.57311517 | G69: =1/(1+WACC!$B$18)^'Breakeven Precio'!G2 -> 0.47605362 | H69: =1/(1+WACC!$B$18)^'Breakeven Precio'!H2 -> 0.3954302 | I69: =1/(1+WACC!$B$18)^'Breakeven Precio'!I2 -> 0.32846099 | J69: =1/(1+WACC!$B$18)^'Breakeven Precio'!J2 -> 0.27283355 | K69: =1/(1+WACC!$B$18)^'Breakeven Precio'!K2 -> 0.22662705 | ... M69: =1/(1+WACC!$B$18)^'Breakeven Precio'!M2 -> 0.15636504 | N69: =1/(1+WACC!$B$18)^11 -> 0.1298834
B70: FCL Descontado | D70: =D63*D69 -> 1.5587623e+09 | E70: =E63*E69 -> 1.7100068e+09 | F70: =F63*F69 -> 1.7653078e+09 | G70: =G63*G69 -> 3.2669902e+09 | H70: =H63*H69 -> -1.1295245e+09 | I70: =I63*I69 -> 2.6176453e+09 | J70: =J63*J69 -> 5.033702e+09 | K70: =K63*K69 -> 4.1401788e+09 | ... N70: =N63*N69 -> 3.5458167e+08
B71: Profitability Index | C71: =ABS(SUM(D70:N70)/C63) -> 1.9212145
B74: ROIC | D74: =D50/D44 -> 0.082020132 | E74: =E50/E44 -> 0.11414362 | F74: =F50/F44 -> 0.1588317 | G74: =G50/G44 -> 0.46613903 | H74: =H50/H44 -> 0.63039467 | I74: =I50/I44 -> 0.866601 | J74: =J50/J44 -> 4.0951245 | K74: =K50/K44 -> 9.1035835 | ... M74: =M50/M44 -> -13.347002
B75: Margen bruto | D75: =D19/D15 -> 0.70879805 | E75: =E19/E15 -> 0.71829263 | F75: =F19/F15 -> 0.72739603 | G75: =G19/G15 -> 0.74474745 | H75: =H19/H15 -> 0.75262953 | I75: =I19/I15 -> 0.76019576 | J75: =J19/J15 -> 0.77325085 | K75: =K19/K15 -> 0.77989586 | ... M75: =M19/M15 -> 0.79241614
B76: Margen EBIT | D76: =D25/D15 -> 0.17509398 | E76: =E25/E15 -> 0.2052876 | F76: =F25/F15 -> 0.23411579 | G76: =G25/G15 -> 0.33770851 | H76: =H25/H15 -> 0.35625719 | I76: =I25/I15 -> 0.37348276 | J76: =J25/J15 -> 0.43845655 | K76: =K25/K15 -> 0.44989437 | ... M76: =M25/M15 -> 0.47087176
B77: Margen EBITDA | D77: =D31/D15 -> 0.28598566 | E77: =E31/E15 -> 0.30413 | F77: =F31/F15 -> 0.32139354 | G77: =G31/G15 -> 0.38921129 | H77: =H31/H15 -> 0.40193504 | I77: =I31/I15 -> 0.41406888 | J77: =J31/J15 -> 0.46016016 | K77: =K31/K15 -> 0.46924428 | ... M77: =M31/M15 -> 0.48623637
B78: Margen KTNO_PKT | D78: =D37/D15 -> 0.031985084 | E78: =E37/E15 -> 0.033922753 | F78: =F37/F15 -> 0.020441521 | G78: =G37/G15 -> -0.04424921 | H78: =H37/H15 -> -0.055726874 | I78: =I37/I15 -> -0.065709448 | J78: =J37/J15 -> -0.099271127 | K78: =K37/K15 -> -0.10409726 | ... M78: =M37/M15 -> -0.10833467
B80: Palanca de crecimiento | D80: =D77/D78 -> 8.9412197 | E80: =E77/E78 -> 8.965369 | F80: =F77/F78 -> 15.722585 | G80: =G77/G78 -> -8.7958924 | H80: =H77/H78 -> -7.2125892 | I80: =I77/I78 -> -6.3015122 | J80: =J77/J78 -> -4.6353877 | K80: =K77/K78 -> -4.5077485 | ... M80: =M77/M78 -> -4.4882802
B81: EVA | D81: =(D74-WACC!$B$18)*'Breakeven Precio'!D44 -> -1.6466343e+09 | E81: =(E74-WACC!$B$18)*'Breakeven Precio'!E44 -> -1.1461225e+09 | F81: =(F74-WACC!$B$18)*'Breakeven Precio'!F44 -> -5.3407325e+08 | G81: =(G74-WACC!$B$18)*'Breakeven Precio'!G44 -> 2.5892261e+09 | H81: =(H74-WACC!$B$18)*'Breakeven Precio'!H44 -> 3.7036344e+09 | I81: =(I74-WACC!$B$18)*'Breakeven Precio'!I44 -> 4.9391944e+09 | J81: =(J74-WACC!$B$18)*'Breakeven Precio'!J44 -> 1.347323e+10 | K81: =(K74-WACC!$B$18)*'Breakeven Precio'!K44 -> 1.595332e+10 | ... M81: =(M74-WACC!$B$18)*'Breakeven Precio'!M44 -> 2.1838461e+10
B86: Nota: El precio debe subir al menos
